{
  "run_date": "2026-04-21",
  "run_timestamp": "2026-04-21T10:23:11Z",
  "screened_count": 1834,
  "qualifying_count": 854,
  "top_picks": [
    {
      "rank": 1,
      "ticker": "FIGS",
      "company_name": "FIGS, Inc.",
      "sector": "Consumer Cyclical",
      "industry": "Apparel Manufacturing",
      "close": 15.99,
      "change_pct": -1.11,
      "volume": 1916900,
      "avg_volume_20d": 2773890,
      "high_52w": 17.48,
      "low_52w": 3.765,
      "dist_from_52w_high_pct": 8.52,
      "composite_score": 81.5,
      "score_breakdown": {
        "trend_score": 81.8,
        "rs_score": 87.4,
        "volume_score": 73.3,
        "momentum_score": 97.0,
        "pattern_score": 64.0,
        "extension_penalty": 1.0
      },
      "indicators": {
        "ema_21": 14.9128,
        "ema_50": 14.0761,
        "ema_150": 11.5651,
        "ema_200": 10.7032,
        "ema_aligned": true,
        "ema_200_slope_pct": 0.272338,
        "rsi_14": 61.81,
        "macd": 0.394,
        "macd_signal": 0.2564,
        "macd_hist": 0.1376,
        "macd_crossover_bullish": true,
        "adx_14": 25.77,
        "adx_trending": true,
        "obv_trend": "rising",
        "cmf_20": 0.0477,
        "rs_3m_percentile": 81.9,
        "rs_6m_percentile": 92.6,
        "ibd_rs_percentile": 88.7,
        "volume_ratio": 0.69,
        "vcp_detected": false,
        "vcp_score": 10.0,
        "vcp_contractions": 7,
        "vcp_tightness": 1.0,
        "squeeze_on": false,
        "squeeze_fired": true,
        "squeeze_bars": 0,
        "squeeze_score": 100.0,
        "extension_ema21_pct": 7.22,
        "extension_ema50_pct": 13.6,
        "atr_pct": 5.51,
        "extension_atr_multiple": 1.22,
        "max_gap_pct": 5.41,
        "is_extended": false,
        "sr_nearest_support": 6.6,
        "sr_support_touches": 3,
        "sr_support_dist_pct": 58.72,
        "sr_near_support": false
      },
      "stage2": true,
      "vcp": false,
      "squeeze": true,
      "chart_url": "https://raw.githubusercontent.com/ilyamiller14/stock-screener/main/results/charts/FIGS_2026-04-21.png"
    },
    {
      "rank": 2,
      "ticker": "KGS",
      "company_name": "Kodiak Gas Services, Inc.",
      "sector": "Energy",
      "industry": "Oil & Gas Equipment & Services",
      "close": 63.42,
      "change_pct": 0.27,
      "volume": 1356000,
      "avg_volume_20d": 1143285,
      "high_52w": 63.83,
      "low_52w": 29.3723,
      "dist_from_52w_high_pct": 0.64,
      "composite_score": 80.4,
      "score_breakdown": {
        "trend_score": 96.9,
        "rs_score": 86.3,
        "volume_score": 74.6,
        "momentum_score": 79.2,
        "pattern_score": 44.8,
        "extension_penalty": 1.0
      },
      "indicators": {
        "ema_21": 59.9285,
        "ema_50": 55.4563,
        "ema_150": 45.9986,
        "ema_200": 43.5372,
        "ema_aligned": true,
        "ema_200_slope_pct": 0.284537,
        "rsi_14": 72.5,
        "macd": 2.1505,
        "macd_signal": 2.0254,
        "macd_hist": 0.1251,
        "macd_crossover_bullish": true,
        "adx_14": 43.77,
        "adx_trending": true,
        "obv_trend": "rising",
        "cmf_20": 0.1799,
        "rs_3m_percentile": 94.8,
        "rs_6m_percentile": 89.3,
        "ibd_rs_percentile": 80.0,
        "volume_ratio": 1.19,
        "vcp_detected": true,
        "vcp_score": 49.6,
        "vcp_contractions": 5,
        "vcp_tightness": 0.737,
        "squeeze_on": false,
        "squeeze_fired": false,
        "squeeze_bars": 0,
        "squeeze_score": 0.0,
        "extension_ema21_pct": 5.83,
        "extension_ema50_pct": 14.36,
        "atr_pct": 2.91,
        "extension_atr_multiple": 1.89,
        "max_gap_pct": 1.62,
        "is_extended": false,
        "sr_nearest_support": 35.32,
        "sr_support_touches": 3,
        "sr_support_dist_pct": 44.3,
        "sr_near_support": false
      },
      "stage2": false,
      "vcp": true,
      "squeeze": false,
      "chart_url": "https://raw.githubusercontent.com/ilyamiller14/stock-screener/main/results/charts/KGS_2026-04-21.png"
    },
    {
      "rank": 3,
      "ticker": "SPHR",
      "company_name": "Sphere Entertainment Co.",
      "sector": "Communication Services",
      "industry": "Entertainment",
      "close": 131.28,
      "change_pct": -3.24,
      "volume": 366600,
      "avg_volume_20d": 702190,
      "high_52w": 137.295,
      "low_52w": 23.89,
      "dist_from_52w_high_pct": 4.38,
      "composite_score": 78.2,
      "score_breakdown": {
        "trend_score": 87.6,
        "rs_score": 89.9,
        "volume_score": 64.8,
        "momentum_score": 96.0,
        "pattern_score": 36.0,
        "extension_penalty": 1.0
      },
      "indicators": {
        "ema_21": 124.8298,
        "ema_50": 115.9619,
        "ema_150": 94.2016,
        "ema_200": 86.6396,
        "ema_aligned": true,
        "ema_200_slope_pct": 0.318638,
        "rsi_14": 61.22,
        "macd": 5.9,
        "macd_signal": 5.1991,
        "macd_hist": 0.7009,
        "macd_crossover_bullish": false,
        "adx_14": 29.88,
        "adx_trending": true,
        "obv_trend": "rising",
        "cmf_20": 0.0812,
        "rs_3m_percentile": 80.9,
        "rs_6m_percentile": 94.1,
        "ibd_rs_percentile": 93.6,
        "volume_ratio": 0.52,
        "vcp_detected": false,
        "vcp_score": 27.4,
        "vcp_contractions": 7,
        "vcp_tightness": 1.368,
        "squeeze_on": false,
        "squeeze_fired": false,
        "squeeze_bars": 0,
        "squeeze_score": 0.0,
        "extension_ema21_pct": 5.17,
        "extension_ema50_pct": 13.21,
        "atr_pct": 4.11,
        "extension_atr_multiple": 1.2,
        "max_gap_pct": 5.11,
        "is_extended": false,
        "sr_nearest_support": 66.03,
        "sr_support_touches": 2,
        "sr_support_dist_pct": 49.7,
        "sr_near_support": false
      },
      "stage2": false,
      "vcp": false,
      "squeeze": false,
      "chart_url": "https://raw.githubusercontent.com/ilyamiller14/stock-screener/main/results/charts/SPHR_2026-04-21.png"
    },
    {
      "rank": 4,
      "ticker": "ESOA",
      "company_name": "Energy Services of America Corporation",
      "sector": "Industrials",
      "industry": "Engineering & Construction",
      "close": 15.14,
      "change_pct": -1.88,
      "volume": 120000,
      "avg_volume_20d": 114785,
      "high_52w": 15.804,
      "low_52w": 7.7367,
      "dist_from_52w_high_pct": 4.2,
      "composite_score": 77.4,
      "score_breakdown": {
        "trend_score": 84.8,
        "rs_score": 82.2,
        "volume_score": 74.8,
        "momentum_score": 95.0,
        "pattern_score": 39.2,
        "extension_penalty": 1.0
      },
      "indicators": {
        "ema_21": 14.1591,
        "ema_50": 13.2835,
        "ema_150": 11.5624,
        "ema_200": 11.1797,
        "ema_aligned": true,
        "ema_200_slope_pct": 0.196883,
        "rsi_14": 63.0,
        "macd": 0.4727,
        "macd_signal": 0.3212,
        "macd_hist": 0.1515,
        "macd_crossover_bullish": true,
        "adx_14": 22.57,
        "adx_trending": true,
        "obv_trend": "rising",
        "cmf_20": 0.0048,
        "rs_3m_percentile": 95.7,
        "rs_6m_percentile": 71.6,
        "ibd_rs_percentile": 78.4,
        "volume_ratio": 1.05,
        "vcp_detected": false,
        "vcp_score": 35.5,
        "vcp_contractions": 6,
        "vcp_tightness": 0.887,
        "squeeze_on": false,
        "squeeze_fired": false,
        "squeeze_bars": 0,
        "squeeze_score": 0.0,
        "extension_ema21_pct": 6.93,
        "extension_ema50_pct": 13.98,
        "atr_pct": 4.45,
        "extension_atr_multiple": 1.46,
        "max_gap_pct": 2.96,
        "is_extended": false,
        "sr_nearest_support": 9.66,
        "sr_support_touches": 4,
        "sr_support_dist_pct": 36.18,
        "sr_near_support": false
      },
      "stage2": false,
      "vcp": false,
      "squeeze": false,
      "chart_url": "https://raw.githubusercontent.com/ilyamiller14/stock-screener/main/results/charts/ESOA_2026-04-21.png"
    },
    {
      "rank": 5,
      "ticker": "CAPR",
      "company_name": "Capricor Therapeutics, Inc.",
      "sector": "Healthcare",
      "industry": "Biotechnology",
      "close": 34.21,
      "change_pct": -1.41,
      "volume": 1038000,
      "avg_volume_20d": 1054465,
      "high_52w": 40.37,
      "low_52w": 4.3,
      "dist_from_52w_high_pct": 15.26,
      "composite_score": 77.3,
      "score_breakdown": {
        "trend_score": 73.2,
        "rs_score": 93.9,
        "volume_score": 71.2,
        "momentum_score": 96.5,
        "pattern_score": 44.7,
        "extension_penalty": 1.0
      },
      "indicators": {
        "ema_21": 32.2239,
        "ema_50": 29.6711,
        "ema_150": 22.6192,
        "ema_200": 20.4552,
        "ema_aligned": true,
        "ema_200_slope_pct": 0.367264,
        "rsi_14": 62.1,
        "macd": 1.5026,
        "macd_signal": 1.2803,
        "macd_hist": 0.2224,
        "macd_crossover_bullish": true,
        "adx_14": 21.1,
        "adx_trending": true,
        "obv_trend": "rising",
        "cmf_20": 0.1482,
        "rs_3m_percentile": 84.8,
        "rs_6m_percentile": 99.3,
        "ibd_rs_percentile": 97.2,
        "volume_ratio": 0.98,
        "vcp_detected": true,
        "vcp_score": 49.3,
        "vcp_contractions": 6,
        "vcp_tightness": 0.719,
        "squeeze_on": false,
        "squeeze_fired": false,
        "squeeze_bars": 0,
        "squeeze_score": 0.0,
        "extension_ema21_pct": 6.16,
        "extension_ema50_pct": 15.3,
        "atr_pct": 6.18,
        "extension_atr_multiple": 0.94,
        "max_gap_pct": 2.82,
        "is_extended": false,
        "sr_nearest_support": 6.09,
        "sr_support_touches": 2,
        "sr_support_dist_pct": 82.21,
        "sr_near_support": false
      },
      "stage2": false,
      "vcp": true,
      "squeeze": false,
      "chart_url": "https://raw.githubusercontent.com/ilyamiller14/stock-screener/main/results/charts/CAPR_2026-04-21.png"
    },
    {
      "rank": 6,
      "ticker": "DSGN",
      "company_name": "Design Therapeutics, Inc.",
      "sector": "Healthcare",
      "industry": "Biotechnology",
      "close": 13.16,
      "change_pct": 0.3,
      "volume": 152800,
      "avg_volume_20d": 295200,
      "high_52w": 13.5,
      "low_52w": 3.105,
      "dist_from_52w_high_pct": 2.52,
      "composite_score": 77.2,
      "score_breakdown": {
        "trend_score": 92.4,
        "rs_score": 89.5,
        "volume_score": 70.7,
        "momentum_score": 70.0,
        "pattern_score": 40.0,
        "extension_penalty": 1.0
      },
      "indicators": {
        "ema_21": 11.9201,
        "ema_50": 11.0758,
        "ema_150": 9.254,
        "ema_200": 8.6017,
        "ema_aligned": true,
        "ema_200_slope_pct": 0.274865,
        "rsi_14": 69.6,
        "macd": 0.6695,
        "macd_signal": 0.5565,
        "macd_hist": 0.113,
        "macd_crossover_bullish": false,
        "adx_14": 37.34,
        "adx_trending": true,
        "obv_trend": "rising",
        "cmf_20": 0.1842,
        "rs_3m_percentile": 85.8,
        "rs_6m_percentile": 93.3,
        "ibd_rs_percentile": 90.2,
        "volume_ratio": 0.52,
        "vcp_detected": false,
        "vcp_score": 37.4,
        "vcp_contractions": 8,
        "vcp_tightness": 1.0,
        "squeeze_on": false,
        "squeeze_fired": false,
        "squeeze_bars": 0,
        "squeeze_score": 0.0,
        "extension_ema21_pct": 10.4,
        "extension_ema50_pct": 18.82,
        "atr_pct": 4.89,
        "extension_atr_multiple": 1.93,
        "max_gap_pct": 4.01,
        "is_extended": false,
        "sr_nearest_support": 9.95,
        "sr_support_touches": 6,
        "sr_support_dist_pct": 24.35,
        "sr_near_support": false
      },
      "stage2": false,
      "vcp": false,
      "squeeze": false,
      "chart_url": "https://raw.githubusercontent.com/ilyamiller14/stock-screener/main/results/charts/DSGN_2026-04-21.png"
    },
    {
      "rank": 7,
      "ticker": "ECPG",
      "company_name": "Encore Capital Group, Inc.",
      "sector": "Financial Services",
      "industry": "Credit Services",
      "close": 82.2,
      "change_pct": 1.8,
      "volume": 235300,
      "avg_volume_20d": 339015,
      "high_52w": 82.66,
      "low_52w": 29.38,
      "dist_from_52w_high_pct": 0.56,
      "composite_score": 76.6,
      "score_breakdown": {
        "trend_score": 98.4,
        "rs_score": 86.3,
        "volume_score": 65.9,
        "momentum_score": 69.1,
        "pattern_score": 35.0,
        "extension_penalty": 1.0
      },
      "indicators": {
        "ema_21": 74.8216,
        "ema_50": 69.19,
        "ema_150": 58.6383,
        "ema_200": 55.795,
        "ema_aligned": true,
        "ema_200_slope_pct": 0.247999,
        "rsi_14": 78.54,
        "macd": 3.6596,
        "macd_signal": 3.0829,
        "macd_hist": 0.5767,
        "macd_crossover_bullish": true,
        "adx_14": 47.49,
        "adx_trending": true,
        "obv_trend": "rising",
        "cmf_20": 0.1512,
        "rs_3m_percentile": 88.3,
        "rs_6m_percentile": 91.7,
        "ibd_rs_percentile": 82.9,
        "volume_ratio": 0.69,
        "vcp_detected": false,
        "vcp_score": 25.1,
        "vcp_contractions": 6,
        "vcp_tightness": 0.737,
        "squeeze_on": false,
        "squeeze_fired": false,
        "squeeze_bars": 0,
        "squeeze_score": 0.0,
        "extension_ema21_pct": 9.86,
        "extension_ema50_pct": 18.8,
        "atr_pct": 3.12,
        "extension_atr_multiple": 2.88,
        "max_gap_pct": 1.68,
        "is_extended": false,
        "sr_nearest_support": 56.22,
        "sr_support_touches": 6,
        "sr_support_dist_pct": 31.61,
        "sr_near_support": false
      },
      "stage2": false,
      "vcp": false,
      "squeeze": false,
      "chart_url": "https://raw.githubusercontent.com/ilyamiller14/stock-screener/main/results/charts/ECPG_2026-04-21.png"
    },
    {
      "rank": 8,
      "ticker": "TK",
      "company_name": "Teekay Corporation Ltd.",
      "sector": "Energy",
      "industry": "Oil & Gas Midstream",
      "close": 13.05,
      "change_pct": 0.62,
      "volume": 386300,
      "avg_volume_20d": 509070,
      "high_52w": 13.76,
      "low_52w": 5.6534,
      "dist_from_52w_high_pct": 5.16,
      "composite_score": 76.5,
      "score_breakdown": {
        "trend_score": 85.9,
        "rs_score": 76.1,
        "volume_score": 76.9,
        "momentum_score": 95.9,
        "pattern_score": 38.8,
        "extension_penalty": 1.0
      },
      "indicators": {
        "ema_21": 12.3999,
        "ema_50": 11.8761,
        "ema_150": 10.4332,
        "ema_200": 9.9345,
        "ema_aligned": true,
        "ema_200_slope_pct": 0.210263,
        "rsi_14": 61.25,
        "macd": 0.2625,
        "macd_signal": 0.2242,
        "macd_hist": 0.0384,
        "macd_crossover_bullish": false,
        "adx_14": 27.61,
        "adx_trending": true,
        "obv_trend": "rising",
        "cmf_20": 0.1703,
        "rs_3m_percentile": 79.7,
        "rs_6m_percentile": 76.8,
        "ibd_rs_percentile": 73.7,
        "volume_ratio": 0.76,
        "vcp_detected": false,
        "vcp_score": 34.5,
        "vcp_contractions": 4,
        "vcp_tightness": 1.64,
        "squeeze_on": false,
        "squeeze_fired": false,
        "squeeze_bars": 0,
        "squeeze_score": 0.0,
        "extension_ema21_pct": 5.24,
        "extension_ema50_pct": 9.88,
        "atr_pct": 4.0,
        "extension_atr_multiple": 1.25,
        "max_gap_pct": 1.73,
        "is_extended": false,
        "sr_nearest_support": 7.41,
        "sr_support_touches": 3,
        "sr_support_dist_pct": 43.22,
        "sr_near_support": false
      },
      "stage2": false,
      "vcp": false,
      "squeeze": false,
      "chart_url": "https://raw.githubusercontent.com/ilyamiller14/stock-screener/main/results/charts/TK_2026-04-21.png"
    },
    {
      "rank": 9,
      "ticker": "SLDB",
      "company_name": "Solid Biosciences Inc.",
      "sector": "Healthcare",
      "industry": "Biotechnology",
      "close": 8.49,
      "change_pct": -1.62,
      "volume": 877900,
      "avg_volume_20d": 1022060,
      "high_52w": 8.866,
      "low_52w": 2.41,
      "dist_from_52w_high_pct": 4.24,
      "composite_score": 76.3,
      "score_breakdown": {
        "trend_score": 83.9,
        "rs_score": 86.1,
        "volume_score": 67.9,
        "momentum_score": 96.1,
        "pattern_score": 33.2,
        "extension_penalty": 1.0
      },
      "indicators": {
        "ema_21": 7.8514,
        "ema_50": 7.2489,
        "ema_150": 6.3441,
        "ema_200": 6.1786,
        "ema_aligned": true,
        "ema_200_slope_pct": 0.208943,
        "rsi_14": 62.32,
        "macd": 0.4154,
        "macd_signal": 0.3565,
        "macd_hist": 0.0588,
        "macd_crossover_bullish": true,
        "adx_14": 20.26,
        "adx_trending": true,
        "obv_trend": "rising",
        "cmf_20": 0.0894,
        "rs_3m_percentile": 91.7,
        "rs_6m_percentile": 58.9,
        "ibd_rs_percentile": 93.7,
        "volume_ratio": 0.86,
        "vcp_detected": false,
        "vcp_score": 20.5,
        "vcp_contractions": 7,
        "vcp_tightness": 1.0,
        "squeeze_on": false,
        "squeeze_fired": false,
        "squeeze_bars": 0,
        "squeeze_score": 0.0,
        "extension_ema21_pct": 8.13,
        "extension_ema50_pct": 17.12,
        "atr_pct": 6.66,
        "extension_atr_multiple": 1.13,
        "max_gap_pct": 4.26,
        "is_extended": false,
        "sr_nearest_support": 5.49,
        "sr_support_touches": 3,
        "sr_support_dist_pct": 35.34,
        "sr_near_support": false
      },
      "stage2": false,
      "vcp": false,
      "squeeze": false,
      "chart_url": "https://raw.githubusercontent.com/ilyamiller14/stock-screener/main/results/charts/SLDB_2026-04-21.png"
    },
    {
      "rank": 10,
      "ticker": "GCT",
      "company_name": "GigaCloud Technology Inc.",
      "sector": "Technology",
      "industry": "Software - Infrastructure",
      "close": 50.09,
      "change_pct": -3.3,
      "volume": 881000,
      "avg_volume_20d": 688495,
      "high_52w": 51.86,
      "low_52w": 11.97,
      "dist_from_52w_high_pct": 3.41,
      "composite_score": 76.1,
      "score_breakdown": {
        "trend_score": 82.4,
        "rs_score": 81.7,
        "volume_score": 66.8,
        "momentum_score": 92.5,
        "pattern_score": 47.2,
        "extension_penalty": 1.0
      },
      "indicators": {
        "ema_21": 45.4615,
        "ema_50": 43.105,
        "ema_150": 37.5087,
        "ema_200": 35.4549,
        "ema_aligned": true,
        "ema_200_slope_pct": 0.2091,
        "rsi_14": 60.92,
        "macd": 1.8514,
        "macd_signal": 1.2767,
        "macd_hist": 0.5746,
        "macd_crossover_bullish": false,
        "adx_14": 14.49,
        "adx_trending": false,
        "obv_trend": "rising",
        "cmf_20": 0.0694,
        "rs_3m_percentile": 65.8,
        "rs_6m_percentile": 88.3,
        "ibd_rs_percentile": 88.6,
        "volume_ratio": 1.28,
        "vcp_detected": false,
        "vcp_score": 30.5,
        "vcp_contractions": 8,
        "vcp_tightness": 0.954,
        "squeeze_on": false,
        "squeeze_fired": true,
        "squeeze_bars": 0,
        "squeeze_score": 100.0,
        "extension_ema21_pct": 10.18,
        "extension_ema50_pct": 16.2,
        "atr_pct": 5.95,
        "extension_atr_multiple": 1.55,
        "max_gap_pct": 8.05,
        "is_extended": false,
        "sr_nearest_support": 33.82,
        "sr_support_touches": 3,
        "sr_support_dist_pct": 32.48,
        "sr_near_support": false
      },
      "stage2": false,
      "vcp": false,
      "squeeze": true,
      "chart_url": "https://raw.githubusercontent.com/ilyamiller14/stock-screener/main/results/charts/GCT_2026-04-21.png"
    },
    {
      "rank": 11,
      "ticker": "GSAT",
      "company_name": "Globalstar, Inc.",
      "sector": "Communication Services",
      "industry": "Telecom Services",
      "close": 80.36,
      "change_pct": 0.42,
      "volume": 2128900,
      "avg_volume_20d": 2258050,
      "high_52w": 81.07,
      "low_52w": 17.24,
      "dist_from_52w_high_pct": 0.88,
      "composite_score": 76.0,
      "score_breakdown": {
        "trend_score": 95.6,
        "rs_score": 85.9,
        "volume_score": 58.4,
        "momentum_score": 75.6,
        "pattern_score": 38.6,
        "extension_penalty": 1.0
      },
      "indicators": {
        "ema_21": 72.4836,
        "ema_50": 67.0112,
        "ema_150": 56.9964,
        "ema_200": 52.7569,
        "ema_aligned": true,
        "ema_200_slope_pct": 0.272303,
        "rsi_14": 66.86,
        "macd": 4.9129,
        "macd_signal": 4.1254,
        "macd_hist": 0.7875,
        "macd_crossover_bullish": false,
        "adx_14": 41.11,
        "adx_trending": true,
        "obv_trend": "rising",
        "cmf_20": 0.1013,
        "rs_3m_percentile": 79.0,
        "rs_6m_percentile": 86.9,
        "ibd_rs_percentile": 89.7,
        "volume_ratio": 0.94,
        "vcp_detected": false,
        "vcp_score": 34.1,
        "vcp_contractions": 7,
        "vcp_tightness": 0.78,
        "squeeze_on": false,
        "squeeze_fired": false,
        "squeeze_bars": 0,
        "squeeze_score": 0.0,
        "extension_ema21_pct": 10.87,
        "extension_ema50_pct": 19.92,
        "atr_pct": 4.97,
        "extension_atr_multiple": 1.97,
        "max_gap_pct": 11.02,
        "is_extended": false,
        "sr_nearest_support": 56.66,
        "sr_support_touches": 3,
        "sr_support_dist_pct": 29.49,
        "sr_near_support": false
      },
      "stage2": false,
      "vcp": false,
      "squeeze": false,
      "chart_url": "https://raw.githubusercontent.com/ilyamiller14/stock-screener/main/results/charts/GSAT_2026-04-21.png"
    },
    {
      "rank": 12,
      "ticker": "HSHP",
      "company_name": "Himalaya Shipping Ltd.",
      "sector": "Industrials",
      "industry": "Marine Shipping",
      "close": 14.25,
      "change_pct": 0.07,
      "volume": 816700,
      "avg_volume_20d": 246235,
      "high_52w": 14.85,
      "low_52w": 4.3672,
      "dist_from_52w_high_pct": 4.04,
      "composite_score": 75.8,
      "score_breakdown": {
        "trend_score": 83.2,
        "rs_score": 89.9,
        "volume_score": 74.2,
        "momentum_score": 96.0,
        "pattern_score": 19.0,
        "extension_penalty": 1.0
      },
      "indicators": {
        "ema_21": 13.5657,
        "ema_50": 12.8282,
        "ema_150": 10.6693,
        "ema_200": 10.0222,
        "ema_aligned": true,
        "ema_200_slope_pct": 0.272264,
        "rsi_14": 61.81,
        "macd": 0.3188,
        "macd_signal": 0.2735,
        "macd_hist": 0.0452,
        "macd_crossover_bullish": false,
        "adx_14": 18.17,
        "adx_trending": false,
        "obv_trend": "rising",
        "cmf_20": 0.0593,
        "rs_3m_percentile": 93.0,
        "rs_6m_percentile": 86.5,
        "ibd_rs_percentile": 89.4,
        "volume_ratio": 3.32,
        "vcp_detected": true,
        "vcp_score": 47.5,
        "vcp_contractions": 5,
        "vcp_tightness": 0.385,
        "squeeze_on": false,
        "squeeze_fired": false,
        "squeeze_bars": 0,
        "squeeze_score": 0.0,
        "extension_ema21_pct": 5.04,
        "extension_ema50_pct": 11.08,
        "atr_pct": 3.53,
        "extension_atr_multiple": 1.36,
        "max_gap_pct": 3.57,
        "is_extended": false,
        "sr_nearest_support": 8.67,
        "sr_support_touches": 4,
        "sr_support_dist_pct": 39.12,
        "sr_near_support": false
      },
      "stage2": false,
      "vcp": true,
      "squeeze": false,
      "chart_url": "https://raw.githubusercontent.com/ilyamiller14/stock-screener/main/results/charts/HSHP_2026-04-21.png"
    },
    {
      "rank": 13,
      "ticker": "CC",
      "company_name": "The Chemours Company",
      "sector": "Basic Materials",
      "industry": "Specialty Chemicals",
      "close": 23.32,
      "change_pct": 0.6,
      "volume": 2256900,
      "avg_volume_20d": 2627600,
      "high_52w": 24.13,
      "low_52w": 8.9658,
      "dist_from_52w_high_pct": 3.36,
      "composite_score": 75.6,
      "score_breakdown": {
        "trend_score": 87.5,
        "rs_score": 82.2,
        "volume_score": 77.7,
        "momentum_score": 80.0,
        "pattern_score": 34.4,
        "extension_penalty": 1.0
      },
      "indicators": {
        "ema_21": 21.7831,
        "ema_50": 19.8518,
        "ema_150": 16.8587,
        "ema_200": 16.3821,
        "ema_aligned": true,
        "ema_200_slope_pct": 0.271794,
        "rsi_14": 64.83,
        "macd": 1.1978,
        "macd_signal": 1.155,
        "macd_hist": 0.0428,
        "macd_crossover_bullish": false,
        "adx_14": 27.09,
        "adx_trending": true,
        "obv_trend": "rising",
        "cmf_20": 0.2771,
        "rs_3m_percentile": 90.4,
        "rs_6m_percentile": 83.8,
        "ibd_rs_percentile": 76.7,
        "volume_ratio": 0.86,
        "vcp_detected": false,
        "vcp_score": 23.4,
        "vcp_contractions": 3,
        "vcp_tightness": 1.873,
        "squeeze_on": false,
        "squeeze_fired": false,
        "squeeze_bars": 0,
        "squeeze_score": 0.0,
        "extension_ema21_pct": 7.06,
        "extension_ema50_pct": 17.47,
        "atr_pct": 4.81,
        "extension_atr_multiple": 1.37,
        "max_gap_pct": 1.85,
        "is_extended": false,
        "sr_nearest_support": 11.55,
        "sr_support_touches": 3,
        "sr_support_dist_pct": 50.47,
        "sr_near_support": false
      },
      "stage2": false,
      "vcp": false,
      "squeeze": false,
      "chart_url": "https://raw.githubusercontent.com/ilyamiller14/stock-screener/main/results/charts/CC_2026-04-21.png"
    },
    {
      "rank": 14,
      "ticker": "CSTM",
      "company_name": "Constellium SE",
      "sector": "Basic Materials",
      "industry": "Aluminum",
      "close": 30.28,
      "change_pct": 2.37,
      "volume": 1609400,
      "avg_volume_20d": 2228870,
      "high_52w": 31.2,
      "low_52w": 8.24,
      "dist_from_52w_high_pct": 2.95,
      "composite_score": 75.4,
      "score_breakdown": {
        "trend_score": 87.5,
        "rs_score": 85.8,
        "volume_score": 68.3,
        "momentum_score": 87.5,
        "pattern_score": 29.0,
        "extension_penalty": 1.0
      },
      "indicators": {
        "ema_21": 27.9385,
        "ema_50": 25.9546,
        "ema_150": 21.6373,
        "ema_200": 20.3847,
        "ema_aligned": true,
        "ema_200_slope_pct": 0.269174,
        "rsi_14": 66.32,
        "macd": 1.4494,
        "macd_signal": 1.2215,
        "macd_hist": 0.2278,
        "macd_crossover_bullish": false,
        "adx_14": 26.11,
        "adx_trending": true,
        "obv_trend": "rising",
        "cmf_20": 0.1491,
        "rs_3m_percentile": 81.5,
        "rs_6m_percentile": 90.2,
        "ibd_rs_percentile": 86.6,
        "volume_ratio": 0.72,
        "vcp_detected": false,
        "vcp_score": 10.0,
        "vcp_contractions": 4,
        "vcp_tightness": 1.063,
        "squeeze_on": false,
        "squeeze_fired": false,
        "squeeze_bars": 0,
        "squeeze_score": 0.0,
        "extension_ema21_pct": 8.38,
        "extension_ema50_pct": 16.67,
        "atr_pct": 4.63,
        "extension_atr_multiple": 1.67,
        "max_gap_pct": 5.13,
        "is_extended": false,
        "sr_nearest_support": 14.76,
        "sr_support_touches": 4,
        "sr_support_dist_pct": 51.27,
        "sr_near_support": false
      },
      "stage2": false,
      "vcp": false,
      "squeeze": false,
      "chart_url": "https://raw.githubusercontent.com/ilyamiller14/stock-screener/main/results/charts/CSTM_2026-04-21.png"
    },
    {
      "rank": 15,
      "ticker": "SPB",
      "company_name": "Spectrum Brands Holdings, Inc.",
      "sector": "Consumer Defensive",
      "industry": "Household & Personal Products",
      "close": 85.41,
      "change_pct": 0.83,
      "volume": 259600,
      "avg_volume_20d": 300810,
      "high_52w": 85.45,
      "low_52w": 49.2745,
      "dist_from_52w_high_pct": 0.05,
      "composite_score": 75.4,
      "score_breakdown": {
        "trend_score": 88.5,
        "rs_score": 68.8,
        "volume_score": 83.7,
        "momentum_score": 79.5,
        "pattern_score": 48.0,
        "extension_penalty": 1.0
      },
      "indicators": {
        "ema_21": 78.4319,
        "ema_50": 75.1072,
        "ema_150": 67.8618,
        "ema_200": 66.8607,
        "ema_aligned": true,
        "ema_200_slope_pct": 0.135791,
        "rsi_14": 72.31,
        "macd": 2.3465,
        "macd_signal": 1.4714,
        "macd_hist": 0.8752,
        "macd_crossover_bullish": true,
        "adx_14": 21.33,
        "adx_trending": true,
        "obv_trend": "rising",
        "cmf_20": 0.3745,
        "rs_3m_percentile": 83.2,
        "rs_6m_percentile": 81.2,
        "ibd_rs_percentile": 55.3,
        "volume_ratio": 0.86,
        "vcp_detected": true,
        "vcp_score": 57.6,
        "vcp_contractions": 6,
        "vcp_tightness": 0.443,
        "squeeze_on": false,
        "squeeze_fired": false,
        "squeeze_bars": 0,
        "squeeze_score": 0.0,
        "extension_ema21_pct": 8.9,
        "extension_ema50_pct": 13.72,
        "atr_pct": 2.8,
        "extension_atr_multiple": 2.92,
        "max_gap_pct": 2.46,
        "is_extended": false,
        "sr_nearest_support": 51.21,
        "sr_support_touches": 4,
        "sr_support_dist_pct": 40.04,
        "sr_near_support": false
      },
      "stage2": false,
      "vcp": true,
      "squeeze": false,
      "chart_url": "https://raw.githubusercontent.com/ilyamiller14/stock-screener/main/results/charts/SPB_2026-04-21.png"
    },
    {
      "rank": 16,
      "ticker": "DHC",
      "company_name": "Diversified Healthcare Trust",
      "sector": "Real Estate",
      "industry": "REIT - Healthcare Facilities",
      "close": 7.37,
      "change_pct": -0.27,
      "volume": 730600,
      "avg_volume_20d": 1403445,
      "high_52w": 7.66,
      "low_52w": 2.0859,
      "dist_from_52w_high_pct": 3.79,
      "composite_score": 75.3,
      "score_breakdown": {
        "trend_score": 84.8,
        "rs_score": 79.7,
        "volume_score": 69.7,
        "momentum_score": 98.7,
        "pattern_score": 31.0,
        "extension_penalty": 1.0
      },
      "indicators": {
        "ema_21": 7.1022,
        "ema_50": 6.7793,
        "ema_150": 5.696,
        "ema_200": 5.3231,
        "ema_aligned": true,
        "ema_200_slope_pct": 0.253645,
        "rsi_14": 59.23,
        "macd": 0.1412,
        "macd_signal": 0.1106,
        "macd_hist": 0.0306,
        "macd_crossover_bullish": true,
        "adx_14": 21.55,
        "adx_trending": true,
        "obv_trend": "rising",
        "cmf_20": 0.0309,
        "rs_3m_percentile": 66.9,
        "rs_6m_percentile": 86.8,
        "ibd_rs_percentile": 84.5,
        "volume_ratio": 0.52,
        "vcp_detected": false,
        "vcp_score": 15.0,
        "vcp_contractions": 7,
        "vcp_tightness": 1.203,
        "squeeze_on": false,
        "squeeze_fired": false,
        "squeeze_bars": 0,
        "squeeze_score": 0.0,
        "extension_ema21_pct": 3.77,
        "extension_ema50_pct": 8.71,
        "atr_pct": 4.08,
        "extension_atr_multiple": 0.89,
        "max_gap_pct": 2.31,
        "is_extended": false,
        "sr_nearest_support": 4.72,
        "sr_support_touches": 4,
        "sr_support_dist_pct": 35.93,
        "sr_near_support": false
      },
      "stage2": false,
      "vcp": false,
      "squeeze": false,
      "chart_url": "https://raw.githubusercontent.com/ilyamiller14/stock-screener/main/results/charts/DHC_2026-04-21.png"
    },
    {
      "rank": 17,
      "ticker": "TDAY",
      "company_name": "USA TODAY Co., Inc.",
      "sector": "Communication Services",
      "industry": "Publishing",
      "close": 7.17,
      "change_pct": -1.92,
      "volume": 1330100,
      "avg_volume_20d": 1950795,
      "high_52w": 7.45,
      "low_52w": 2.96,
      "dist_from_52w_high_pct": 3.76,
      "composite_score": 75.3,
      "score_breakdown": {
        "trend_score": 84.3,
        "rs_score": 72.3,
        "volume_score": 65.4,
        "momentum_score": 88.9,
        "pattern_score": 58.6,
        "extension_penalty": 1.0
      },
      "indicators": {
        "ema_21": 6.969,
        "ema_50": 6.5855,
        "ema_150": 5.6953,
        "ema_200": 5.4301,
        "ema_aligned": true,
        "ema_200_slope_pct": 0.244337,
        "rsi_14": 60.05,
        "macd": 0.2204,
        "macd_signal": 0.2148,
        "macd_hist": 0.0056,
        "macd_crossover_bullish": false,
        "adx_14": 20.17,
        "adx_trending": true,
        "obv_trend": "rising",
        "cmf_20": 0.0098,
        "rs_3m_percentile": 61.2,
        "rs_6m_percentile": 90.6,
        "ibd_rs_percentile": 71.7,
        "volume_ratio": 0.68,
        "vcp_detected": true,
        "vcp_score": 84.1,
        "vcp_contractions": 8,
        "vcp_tightness": 0.557,
        "squeeze_on": false,
        "squeeze_fired": false,
        "squeeze_bars": 0,
        "squeeze_score": 0.0,
        "extension_ema21_pct": 2.88,
        "extension_ema50_pct": 8.88,
        "atr_pct": 3.51,
        "extension_atr_multiple": 0.8,
        "max_gap_pct": 2.0,
        "is_extended": false,
        "sr_nearest_support": 4.38,
        "sr_support_touches": 4,
        "sr_support_dist_pct": 38.91,
        "sr_near_support": false
      },
      "stage2": false,
      "vcp": true,
      "squeeze": false,
      "chart_url": "https://raw.githubusercontent.com/ilyamiller14/stock-screener/main/results/charts/TDAY_2026-04-21.png"
    },
    {
      "rank": 18,
      "ticker": "PKST",
      "company_name": "Peakstone Realty Trust",
      "sector": "Real Estate",
      "industry": "REIT - Office",
      "close": 20.95,
      "change_pct": 0.05,
      "volume": 263700,
      "avg_volume_20d": 272115,
      "high_52w": 20.97,
      "low_52w": 10.4637,
      "dist_from_52w_high_pct": 0.1,
      "composite_score": 75.3,
      "score_breakdown": {
        "trend_score": 99.9,
        "rs_score": 77.9,
        "volume_score": 71.1,
        "momentum_score": 18.7,
        "pattern_score": 82.6,
        "extension_penalty": 1.0
      },
      "indicators": {
        "ema_21": 20.8689,
        "ema_50": 20.1016,
        "ema_150": 17.273,
        "ema_200": 16.4357,
        "ema_aligned": true,
        "ema_200_slope_pct": 0.235057,
        "rsi_14": 78.81,
        "macd": 0.1265,
        "macd_signal": 0.1697,
        "macd_hist": -0.0432,
        "macd_crossover_bullish": false,
        "adx_14": 67.59,
        "adx_trending": true,
        "obv_trend": "rising",
        "cmf_20": -0.035,
        "rs_3m_percentile": 89.8,
        "rs_6m_percentile": 82.3,
        "ibd_rs_percentile": 69.1,
        "volume_ratio": 0.97,
        "vcp_detected": true,
        "vcp_score": 74.0,
        "vcp_contractions": 6,
        "vcp_tightness": 0.064,
        "squeeze_on": true,
        "squeeze_fired": false,
        "squeeze_bars": 20,
        "squeeze_score": 80.0,
        "extension_ema21_pct": 0.39,
        "extension_ema50_pct": 4.22,
        "atr_pct": 0.22,
        "extension_atr_multiple": 1.73,
        "max_gap_pct": 0.24,
        "is_extended": false,
        "sr_nearest_support": 20.86,
        "sr_support_touches": 5,
        "sr_support_dist_pct": 0.43,
        "sr_near_support": true
      },
      "stage2": true,
      "vcp": true,
      "squeeze": true,
      "chart_url": "https://raw.githubusercontent.com/ilyamiller14/stock-screener/main/results/charts/PKST_2026-04-21.png"
    },
    {
      "rank": 19,
      "ticker": "INSW",
      "company_name": "International Seaways, Inc.",
      "sector": "Energy",
      "industry": "Oil & Gas Midstream",
      "close": 77.46,
      "change_pct": 1.29,
      "volume": 348400,
      "avg_volume_20d": 476845,
      "high_52w": 78.4,
      "low_52w": 29.0783,
      "dist_from_52w_high_pct": 1.2,
      "composite_score": 74.9,
      "score_breakdown": {
        "trend_score": 90.7,
        "rs_score": 82.5,
        "volume_score": 59.0,
        "momentum_score": 93.5,
        "pattern_score": 27.5,
        "extension_penalty": 1.0
      },
      "indicators": {
        "ema_21": 73.4329,
        "ema_50": 69.0051,
        "ema_150": 58.2163,
        "ema_200": 55.1367,
        "ema_aligned": true,
        "ema_200_slope_pct": 0.267559,
        "rsi_14": 62.09,
        "macd": 2.1065,
        "macd_signal": 2.0595,
        "macd_hist": 0.047,
        "macd_crossover_bullish": false,
        "adx_14": 29.73,
        "adx_trending": true,
        "obv_trend": "rising",
        "cmf_20": 0.1032,
        "rs_3m_percentile": 85.6,
        "rs_6m_percentile": 87.1,
        "ibd_rs_percentile": 78.9,
        "volume_ratio": 0.73,
        "vcp_detected": false,
        "vcp_score": 1.9,
        "vcp_contractions": 2,
        "vcp_tightness": 1.356,
        "squeeze_on": true,
        "squeeze_fired": false,
        "squeeze_bars": 1,
        "squeeze_score": 5.0,
        "extension_ema21_pct": 5.48,
        "extension_ema50_pct": 12.25,
        "atr_pct": 4.24,
        "extension_atr_multiple": 1.23,
        "max_gap_pct": 2.77,
        "is_extended": false,
        "sr_nearest_support": 46.85,
        "sr_support_touches": 3,
        "sr_support_dist_pct": 39.52,
        "sr_near_support": false
      },
      "stage2": false,
      "vcp": false,
      "squeeze": true,
      "chart_url": "https://raw.githubusercontent.com/ilyamiller14/stock-screener/main/results/charts/INSW_2026-04-21.png"
    },
    {
      "rank": 20,
      "ticker": "MITK",
      "company_name": "Mitek Systems, Inc.",
      "sector": "Technology",
      "industry": "Software - Application",
      "close": 14.95,
      "change_pct": -1.32,
      "volume": 674400,
      "avg_volume_20d": 833555,
      "high_52w": 15.61,
      "low_52w": 7.54,
      "dist_from_52w_high_pct": 4.23,
      "composite_score": 73.9,
      "score_breakdown": {
        "trend_score": 80.1,
        "rs_score": 78.9,
        "volume_score": 66.7,
        "momentum_score": 96.5,
        "pattern_score": 37.4,
        "extension_penalty": 1.0
      },
      "indicators": {
        "ema_21": 14.1968,
        "ema_50": 13.5239,
        "ema_150": 11.8038,
        "ema_200": 11.3983,
        "ema_aligned": true,
        "ema_200_slope_pct": 0.187997,
        "rsi_14": 57.9,
        "macd": 0.2801,
        "macd_signal": 0.1856,
        "macd_hist": 0.0945,
        "macd_crossover_bullish": true,
        "adx_14": 10.89,
        "adx_trending": false,
        "obv_trend": "rising",
        "cmf_20": -0.0471,
        "rs_3m_percentile": 89.4,
        "rs_6m_percentile": 81.8,
        "ibd_rs_percentile": 71.5,
        "volume_ratio": 0.81,
        "vcp_detected": false,
        "vcp_score": 6.0,
        "vcp_contractions": 6,
        "vcp_tightness": 1.129,
        "squeeze_on": false,
        "squeeze_fired": true,
        "squeeze_bars": 0,
        "squeeze_score": 100.0,
        "extension_ema21_pct": 5.31,
        "extension_ema50_pct": 10.54,
        "atr_pct": 4.98,
        "extension_atr_multiple": 1.01,
        "max_gap_pct": 4.9,
        "is_extended": false,
        "sr_nearest_support": 10.59,
        "sr_support_touches": 5,
        "sr_support_dist_pct": 29.16,
        "sr_near_support": false
      },
      "stage2": false,
      "vcp": false,
      "squeeze": true,
      "chart_url": "https://raw.githubusercontent.com/ilyamiller14/stock-screener/main/results/charts/MITK_2026-04-21.png"
    }
  ],
  "macro": {
    "etfs": [
      {
        "ticker": "XLY",
        "interest_score": 80,
        "narrative": "Breaking below support at 120.40 (3 touches)",
        "sr_levels": [
          {
            "price": 114.0253,
            "touches": 6,
            "type": "support"
          },
          {
            "price": 117.5753,
            "touches": 6,
            "type": "support"
          },
          {
            "price": 104.4197,
            "touches": 4,
            "type": "support"
          },
          {
            "price": 107.4256,
            "touches": 3,
            "type": "support"
          },
          {
            "price": 120.3959,
            "touches": 3,
            "type": "resistance"
          }
        ],
        "rsi": 66.6,
        "chart_url": "https://raw.githubusercontent.com/ilyamiller14/stock-screener/main/results/charts/macro_XLY_2026-04-21.png",
        "chart_generated": true
      },
      {
        "ticker": "XLF",
        "interest_score": 80,
        "narrative": "Breaking above resistance at 52.56 (9 touches)",
        "sr_levels": [
          {
            "price": 52.5606,
            "touches": 9,
            "type": "support"
          },
          {
            "price": 50.7169,
            "touches": 8,
            "type": "support"
          },
          {
            "price": 53.8241,
            "touches": 6,
            "type": "resistance"
          },
          {
            "price": 49.2002,
            "touches": 3,
            "type": "support"
          },
          {
            "price": 55.7783,
            "touches": 2,
            "type": "resistance"
          }
        ],
        "rsi": 67.6,
        "chart_url": "https://raw.githubusercontent.com/ilyamiller14/stock-screener/main/results/charts/macro_XLF_2026-04-21.png",
        "chart_generated": true
      },
      {
        "ticker": "KRE",
        "interest_score": 65,
        "narrative": "Breaking above resistance at 69.85 (3 touches)",
        "sr_levels": [
          {
            "price": 62.2193,
            "touches": 7,
            "type": "support"
          },
          {
            "price": 57.761,
            "touches": 5,
            "type": "support"
          },
          {
            "price": 60.4881,
            "touches": 3,
            "type": "support"
          },
          {
            "price": 64.9394,
            "touches": 3,
            "type": "support"
          },
          {
            "price": 69.85,
            "touches": 3,
            "type": "support"
          }
        ],
        "rsi": 68.9,
        "chart_url": "https://raw.githubusercontent.com/ilyamiller14/stock-screener/main/results/charts/macro_KRE_2026-04-21.png",
        "chart_generated": true
      },
      {
        "ticker": "SPY",
        "interest_score": 60,
        "narrative": "Breaking above resistance at 689.88 (6 touches) | Overbought",
        "sr_levels": [
          {
            "price": 672.5168,
            "touches": 8,
            "type": "support"
          },
          {
            "price": 689.881,
            "touches": 6,
            "type": "support"
          },
          {
            "price": 631.97,
            "touches": 5,
            "type": "support"
          },
          {
            "price": 589.2816,
            "touches": 3,
            "type": "support"
          },
          {
            "price": 649.3228,
            "touches": 3,
            "type": "support"
          }
        ],
        "rsi": 72.2,
        "chart_url": "https://raw.githubusercontent.com/ilyamiller14/stock-screener/main/results/charts/macro_SPY_2026-04-21.png",
        "chart_generated": true
      },
      {
        "ticker": "QQQ",
        "interest_score": 60,
        "narrative": "Breaking above resistance at 626.38 (5 touches) | Overbought",
        "sr_levels": [
          {
            "price": 561.1962,
            "touches": 5,
            "type": "support"
          },
          {
            "price": 596.2782,
            "touches": 5,
            "type": "support"
          },
          {
            "price": 626.3802,
            "touches": 5,
            "type": "support"
          },
          {
            "price": 611.1161,
            "touches": 4,
            "type": "support"
          },
          {
            "price": 578.1931,
            "touches": 3,
            "type": "support"
          }
        ],
        "rsi": 72.8,
        "chart_url": "https://raw.githubusercontent.com/ilyamiller14/stock-screener/main/results/charts/macro_QQQ_2026-04-21.png",
        "chart_generated": true
      }
    ],
    "ratios": [
      {
        "pair": "XLK/XLP",
        "name": "Tech / Staples",
        "rising": "Growth leadership",
        "falling": "Defensive mode",
        "interest_score": 84,
        "narrative": "Breaking below support at 1.89 (2 touches) | Overbought",
        "sr_levels": [
          {
            "price": 1.6017,
            "touches": 4,
            "type": "support"
          },
          {
            "price": 1.6809,
            "touches": 4,
            "type": "support"
          },
          {
            "price": 1.5572,
            "touches": 3,
            "type": "support"
          },
          {
            "price": 1.8207,
            "touches": 3,
            "type": "support"
          },
          {
            "price": 1.6323,
            "touches": 2,
            "type": "support"
          }
        ],
        "rsi": 74.1,
        "chart_url": "https://raw.githubusercontent.com/ilyamiller14/stock-screener/main/results/charts/ratio_XLK_XLP_2026-04-21.png",
        "chart_generated": true
      },
      {
        "pair": "XLY/XLP",
        "name": "Discretionary / Staples",
        "rising": "Risk appetite",
        "falling": "Defensive rotation",
        "interest_score": 80,
        "narrative": "Breaking above resistance at 1.45 (3 touches)",
        "sr_levels": [
          {
            "price": 1.3773,
            "touches": 6,
            "type": "support"
          },
          {
            "price": 1.3495,
            "touches": 5,
            "type": "support"
          },
          {
            "price": 1.3042,
            "touches": 4,
            "type": "support"
          },
          {
            "price": 1.4489,
            "touches": 3,
            "type": "support"
          },
          {
            "price": 1.4803,
            "touches": 3,
            "type": "resistance"
          }
        ],
        "rsi": 67.7,
        "chart_url": "https://raw.githubusercontent.com/ilyamiller14/stock-screener/main/results/charts/ratio_XLY_XLP_2026-04-21.png",
        "chart_generated": true
      },
      {
        "pair": "SPHB/SPLV",
        "name": "High Beta / Low Vol",
        "rising": "Risk-on",
        "falling": "Risk-off",
        "interest_score": 60,
        "narrative": "Breaking above resistance at 1.70 (3 touches) | Overbought",
        "sr_levels": [
          {
            "price": 1.6568,
            "touches": 5,
            "type": "support"
          },
          {
            "price": 1.4331,
            "touches": 4,
            "type": "support"
          },
          {
            "price": 1.5487,
            "touches": 4,
            "type": "support"
          },
          {
            "price": 1.3891,
            "touches": 3,
            "type": "support"
          },
          {
            "price": 1.7027,
            "touches": 3,
            "type": "support"
          }
        ],
        "rsi": 73.0,
        "chart_url": "https://raw.githubusercontent.com/ilyamiller14/stock-screener/main/results/charts/ratio_SPHB_SPLV_2026-04-21.png",
        "chart_generated": true
      }
    ]
  }
}