{
  "run_date": "2026-05-15",
  "run_timestamp": "2026-05-15T20:30:35Z",
  "scorer_version": "2.0",
  "scorer_revised_at": "2026-05-15",
  "screened_count": 1873,
  "qualifying_count": 169,
  "top_picks": [
    {
      "rank": 1,
      "ticker": "ATEN",
      "company_name": "A10 Networks, Inc.",
      "sector": "Technology",
      "industry": "Software - Infrastructure",
      "close": 27.95,
      "change_pct": -0.29,
      "volume": 918573,
      "avg_volume_20d": 1023193,
      "high_52w": 28.66,
      "low_52w": 16.4713,
      "dist_from_52w_high_pct": 2.48,
      "composite_score": 51.5,
      "score_breakdown": {
        "trend_strength": 86.3,
        "trend_cleanliness": 100.0,
        "rs": 46.1,
        "base_setup": 28.8,
        "volume_profile": 44.8,
        "raw_setup_score": 60.6,
        "penalty_multiplier": 0.85,
        "penalty_triggered": [
          "climactic_mild",
          "52w_low_mild"
        ],
        "composite_score": 51.5
      },
      "indicators": {
        "ema_21": 26.9929,
        "ema_50": 25.0848,
        "ema_150": 21.5816,
        "ema_200": 20.711,
        "ema_aligned": true,
        "ema_200_slope_pct": 0.26007,
        "rsi_14": 62.35,
        "macd": 0.8316,
        "macd_signal": 0.939,
        "macd_hist": -0.1075,
        "macd_crossover_bullish": false,
        "adx_14": 24.02,
        "adx_trending": true,
        "obv_trend": "rising",
        "cmf_20": 0.2539,
        "rs_3m_percentile": 63.7,
        "rs_6m_percentile": 63.1,
        "ibd_rs_percentile": 39.3,
        "volume_ratio": 0.9,
        "vcp_detected": false,
        "vcp_score": 6.0,
        "vcp_contractions": 6,
        "vcp_tightness": 1.716,
        "squeeze_on": true,
        "squeeze_fired": false,
        "squeeze_bars": 3,
        "squeeze_score": 15.0,
        "extension_ema21_pct": 3.55,
        "extension_ema50_pct": 11.42,
        "atr_pct": 3.64,
        "extension_atr_multiple": 0.94,
        "max_gap_pct": 4.03,
        "is_extended": false,
        "sr_nearest_support": 17.05,
        "sr_support_touches": 6,
        "sr_support_dist_pct": 38.99,
        "sr_near_support": false
      },
      "stage2": false,
      "vcp": false,
      "squeeze": true,
      "chart_url": "https://raw.githubusercontent.com/ilyamiller14/stock-screener/main/results/charts/ATEN_2026-05-15.png"
    },
    {
      "rank": 2,
      "ticker": "MIAX",
      "company_name": "Miami International Holdings, Inc.",
      "sector": "Financial Services",
      "industry": "Capital Markets",
      "close": 56.16,
      "change_pct": -1.2,
      "volume": 1094295,
      "avg_volume_20d": 1182134,
      "high_52w": 57.14,
      "low_52w": 28.63,
      "dist_from_52w_high_pct": 1.72,
      "composite_score": 47.9,
      "score_breakdown": {
        "trend_strength": 75.5,
        "trend_cleanliness": 67.5,
        "rs": 59.2,
        "base_setup": 24.1,
        "volume_profile": 51.7,
        "raw_setup_score": 56.4,
        "penalty_multiplier": 0.85,
        "penalty_triggered": [
          "52w_low_mild"
        ],
        "composite_score": 47.9
      },
      "indicators": {
        "ema_21": 49.5221,
        "ema_50": 45.9645,
        "ema_150": 42.66,
        "ema_200": 41.5022,
        "ema_aligned": true,
        "ema_200_slope_pct": 0.146558,
        "rsi_14": 83.33,
        "macd": 3.267,
        "macd_signal": 2.5014,
        "macd_hist": 0.7656,
        "macd_crossover_bullish": false,
        "adx_14": 51.75,
        "adx_trending": true,
        "obv_trend": "rising",
        "cmf_20": 0.4696,
        "rs_3m_percentile": 61.3,
        "rs_6m_percentile": 2.4,
        "ibd_rs_percentile": 56.5,
        "volume_ratio": 0.93,
        "vcp_detected": true,
        "vcp_score": 60.3,
        "vcp_contractions": 6,
        "vcp_tightness": 0.638,
        "squeeze_on": false,
        "squeeze_fired": false,
        "squeeze_bars": 0,
        "squeeze_score": 0.0,
        "extension_ema21_pct": 13.4,
        "extension_ema50_pct": 22.18,
        "atr_pct": 3.33,
        "extension_atr_multiple": 3.55,
        "max_gap_pct": 2.18,
        "is_extended": false,
        "sr_nearest_support": 41.85,
        "sr_support_touches": 5,
        "sr_support_dist_pct": 25.48,
        "sr_near_support": false
      },
      "stage2": false,
      "vcp": true,
      "squeeze": false,
      "chart_url": "https://raw.githubusercontent.com/ilyamiller14/stock-screener/main/results/charts/MIAX_2026-05-15.png"
    },
    {
      "rank": 3,
      "ticker": "EBAY",
      "company_name": "eBay Inc.",
      "sector": "Consumer Cyclical",
      "industry": "Internet Retail",
      "close": 116.13,
      "change_pct": 2.55,
      "volume": 5748797,
      "avg_volume_20d": 7343149,
      "high_52w": 116.83,
      "low_52w": 68.4461,
      "dist_from_52w_high_pct": 0.6,
      "composite_score": 46.7,
      "score_breakdown": {
        "trend_strength": 71.0,
        "trend_cleanliness": 95.0,
        "rs": 63.4,
        "base_setup": 2.4,
        "volume_profile": 43.8,
        "raw_setup_score": 54.9,
        "penalty_multiplier": 0.85,
        "penalty_triggered": [
          "52w_low_mild"
        ],
        "composite_score": 46.7
      },
      "indicators": {
        "ema_21": 106.567,
        "ema_50": 100.662,
        "ema_150": 92.6006,
        "ema_200": 89.9147,
        "ema_aligned": true,
        "ema_200_slope_pct": 0.153108,
        "rsi_14": 71.84,
        "macd": 4.1704,
        "macd_signal": 3.5057,
        "macd_hist": 0.6647,
        "macd_crossover_bullish": true,
        "adx_14": 22.91,
        "adx_trending": true,
        "obv_trend": "rising",
        "cmf_20": 0.1522,
        "rs_3m_percentile": 70.8,
        "rs_6m_percentile": 29.2,
        "ibd_rs_percentile": 53.0,
        "volume_ratio": 0.78,
        "vcp_detected": false,
        "vcp_score": 6.0,
        "vcp_contractions": 6,
        "vcp_tightness": 1.983,
        "squeeze_on": false,
        "squeeze_fired": false,
        "squeeze_bars": 0,
        "squeeze_score": 0.0,
        "extension_ema21_pct": 8.97,
        "extension_ema50_pct": 15.37,
        "atr_pct": 3.22,
        "extension_atr_multiple": 2.56,
        "max_gap_pct": 4.87,
        "is_extended": false,
        "sr_nearest_support": 87.94,
        "sr_support_touches": 5,
        "sr_support_dist_pct": 24.27,
        "sr_near_support": false
      },
      "stage2": false,
      "vcp": false,
      "squeeze": false,
      "chart_url": "https://raw.githubusercontent.com/ilyamiller14/stock-screener/main/results/charts/EBAY_2026-05-15.png"
    },
    {
      "rank": 4,
      "ticker": "CWAN",
      "company_name": "Clearwater Analytics Holdings, Inc.",
      "sector": "Technology",
      "industry": "Software - Application",
      "close": 24.35,
      "change_pct": -0.08,
      "volume": 1745900,
      "avg_volume_20d": 3366775,
      "high_52w": 25.069,
      "low_52w": 15.735,
      "dist_from_52w_high_pct": 2.87,
      "composite_score": 45.8,
      "score_breakdown": {
        "trend_strength": 54.9,
        "trend_cleanliness": 93.8,
        "rs": 3.0,
        "base_setup": 62.9,
        "volume_profile": 31.1,
        "raw_setup_score": 45.8,
        "penalty_multiplier": 1.0,
        "penalty_triggered": [],
        "composite_score": 45.8
      },
      "indicators": {
        "ema_21": 24.2095,
        "ema_50": 23.9445,
        "ema_150": 23.0714,
        "ema_200": 22.8877,
        "ema_aligned": true,
        "ema_200_slope_pct": 0.060993,
        "rsi_14": 69.39,
        "macd": 0.1287,
        "macd_signal": 0.1358,
        "macd_hist": -0.0071,
        "macd_crossover_bullish": false,
        "adx_14": 36.04,
        "adx_trending": true,
        "obv_trend": "rising",
        "cmf_20": -0.0678,
        "rs_3m_percentile": 6.5,
        "rs_6m_percentile": 17.3,
        "ibd_rs_percentile": 0.0,
        "volume_ratio": 0.52,
        "vcp_detected": true,
        "vcp_score": 94.0,
        "vcp_contractions": 6,
        "vcp_tightness": 0.096,
        "squeeze_on": false,
        "squeeze_fired": false,
        "squeeze_bars": 0,
        "squeeze_score": 0.0,
        "extension_ema21_pct": 0.58,
        "extension_ema50_pct": 1.69,
        "atr_pct": 0.36,
        "extension_atr_multiple": 1.6,
        "max_gap_pct": 8.43,
        "is_extended": false,
        "sr_nearest_support": 24.19,
        "sr_support_touches": 5,
        "sr_support_dist_pct": 0.66,
        "sr_near_support": true
      },
      "stage2": false,
      "vcp": true,
      "squeeze": false,
      "chart_url": "https://raw.githubusercontent.com/ilyamiller14/stock-screener/main/results/charts/CWAN_2026-05-15.png"
    },
    {
      "rank": 5,
      "ticker": "BK",
      "company_name": "The Bank of New York Mellon Corporation",
      "sector": "Financial Services",
      "industry": "Banks - Diversified",
      "close": 135.02,
      "change_pct": -0.71,
      "volume": 3249861,
      "avg_volume_20d": 3556493,
      "high_52w": 138.5998,
      "low_52w": 85.7977,
      "dist_from_52w_high_pct": 2.58,
      "composite_score": 45.7,
      "score_breakdown": {
        "trend_strength": 68.4,
        "trend_cleanliness": 82.1,
        "rs": 21.8,
        "base_setup": 30.8,
        "volume_profile": 31.1,
        "raw_setup_score": 45.7,
        "penalty_multiplier": 1.0,
        "penalty_triggered": [],
        "composite_score": 45.7
      },
      "indicators": {
        "ema_21": 132.3677,
        "ema_50": 128.0198,
        "ema_150": 118.3968,
        "ema_200": 114.2493,
        "ema_aligned": true,
        "ema_200_slope_pct": 0.154837,
        "rsi_14": 60.66,
        "macd": 2.0219,
        "macd_signal": 2.2993,
        "macd_hist": -0.2774,
        "macd_crossover_bullish": false,
        "adx_14": 29.65,
        "adx_trending": true,
        "obv_trend": "rising",
        "cmf_20": -0.065,
        "rs_3m_percentile": 24.4,
        "rs_6m_percentile": 13.1,
        "ibd_rs_percentile": 22.0,
        "volume_ratio": 0.91,
        "vcp_detected": false,
        "vcp_score": 25.2,
        "vcp_contractions": 9,
        "vcp_tightness": 0.853,
        "squeeze_on": false,
        "squeeze_fired": false,
        "squeeze_bars": 0,
        "squeeze_score": 0.0,
        "extension_ema21_pct": 2.0,
        "extension_ema50_pct": 5.47,
        "atr_pct": 2.04,
        "extension_atr_multiple": 0.96,
        "max_gap_pct": 2.06,
        "is_extended": false,
        "sr_nearest_support": 114.55,
        "sr_support_touches": 6,
        "sr_support_dist_pct": 15.16,
        "sr_near_support": false
      },
      "stage2": false,
      "vcp": false,
      "squeeze": false,
      "chart_url": "https://raw.githubusercontent.com/ilyamiller14/stock-screener/main/results/charts/BK_2026-05-15.png"
    },
    {
      "rank": 6,
      "ticker": "CASY",
      "company_name": "Casey's General Stores, Inc.",
      "sector": "Consumer Cyclical",
      "industry": "Specialty Retail",
      "close": 852.75,
      "change_pct": -2.82,
      "volume": 788218,
      "avg_volume_20d": 384420,
      "high_52w": 901.0,
      "low_52w": 428.3594,
      "dist_from_52w_high_pct": 5.36,
      "composite_score": 45.5,
      "score_breakdown": {
        "trend_strength": 92.7,
        "trend_cleanliness": 98.7,
        "rs": 50.7,
        "base_setup": 26.3,
        "volume_profile": 60.6,
        "raw_setup_score": 65.0,
        "penalty_multiplier": 0.7,
        "penalty_triggered": [
          "reversal_mild",
          "52w_low_mild"
        ],
        "composite_score": 45.5
      },
      "indicators": {
        "ema_21": 829.2768,
        "ema_50": 772.619,
        "ema_150": 669.6544,
        "ema_200": 637.796,
        "ema_aligned": true,
        "ema_200_slope_pct": 0.256854,
        "rsi_14": 61.28,
        "macd": 34.7438,
        "macd_signal": 34.8607,
        "macd_hist": -0.1169,
        "macd_crossover_bullish": false,
        "adx_14": 44.83,
        "adx_trending": true,
        "obv_trend": "rising",
        "cmf_20": 0.2252,
        "rs_3m_percentile": 53.6,
        "rs_6m_percentile": 56.5,
        "ibd_rs_percentile": 48.8,
        "volume_ratio": 2.05,
        "vcp_detected": false,
        "vcp_score": 12.0,
        "vcp_contractions": 6,
        "vcp_tightness": 1.364,
        "squeeze_on": false,
        "squeeze_fired": false,
        "squeeze_bars": 0,
        "squeeze_score": 0.0,
        "extension_ema21_pct": 2.83,
        "extension_ema50_pct": 10.37,
        "atr_pct": 2.47,
        "extension_atr_multiple": 1.11,
        "max_gap_pct": 2.13,
        "is_extended": false,
        "sr_nearest_support": 565.93,
        "sr_support_touches": 5,
        "sr_support_dist_pct": 33.63,
        "sr_near_support": false
      },
      "stage2": false,
      "vcp": false,
      "squeeze": false,
      "chart_url": "https://raw.githubusercontent.com/ilyamiller14/stock-screener/main/results/charts/CASY_2026-05-15.png"
    },
    {
      "rank": 7,
      "ticker": "VRSN",
      "company_name": "VeriSign, Inc.",
      "sector": "Technology",
      "industry": "Software - Infrastructure",
      "close": 297.57,
      "change_pct": 1.58,
      "volume": 684128,
      "avg_volume_20d": 836021,
      "high_52w": 307.609,
      "low_52w": 208.0859,
      "dist_from_52w_high_pct": 3.26,
      "composite_score": 43.6,
      "score_breakdown": {
        "trend_strength": 58.4,
        "trend_cleanliness": 100.0,
        "rs": 23.2,
        "base_setup": 10.2,
        "volume_profile": 41.1,
        "raw_setup_score": 43.6,
        "penalty_multiplier": 1.0,
        "penalty_triggered": [],
        "composite_score": 43.6
      },
      "indicators": {
        "ema_21": 279.4472,
        "ema_50": 266.7601,
        "ema_150": 255.5516,
        "ema_200": 253.0561,
        "ema_aligned": true,
        "ema_200_slope_pct": 0.090797,
        "rsi_14": 72.0,
        "macd": 8.4645,
        "macd_signal": 7.0259,
        "macd_hist": 1.4386,
        "macd_crossover_bullish": true,
        "adx_14": 25.14,
        "adx_trending": true,
        "obv_trend": "rising",
        "cmf_20": 0.2815,
        "rs_3m_percentile": 66.1,
        "rs_6m_percentile": 10.1,
        "ibd_rs_percentile": 13.7,
        "volume_ratio": 0.82,
        "vcp_detected": false,
        "vcp_score": 25.4,
        "vcp_contractions": 6,
        "vcp_tightness": 1.956,
        "squeeze_on": false,
        "squeeze_fired": false,
        "squeeze_bars": 0,
        "squeeze_score": 0.0,
        "extension_ema21_pct": 6.49,
        "extension_ema50_pct": 11.55,
        "atr_pct": 2.52,
        "extension_atr_multiple": 2.41,
        "max_gap_pct": 1.85,
        "is_extended": false,
        "sr_nearest_support": 243.78,
        "sr_support_touches": 5,
        "sr_support_dist_pct": 18.08,
        "sr_near_support": false
      },
      "stage2": false,
      "vcp": false,
      "squeeze": false,
      "chart_url": "https://raw.githubusercontent.com/ilyamiller14/stock-screener/main/results/charts/VRSN_2026-05-15.png"
    },
    {
      "rank": 8,
      "ticker": "HPE",
      "company_name": "Hewlett Packard Enterprise Company",
      "sector": "Technology",
      "industry": "Communication Equipment",
      "close": 33.1,
      "change_pct": -3.02,
      "volume": 14092801,
      "avg_volume_20d": 15586200,
      "high_52w": 34.695,
      "low_52w": 16.6049,
      "dist_from_52w_high_pct": 4.6,
      "composite_score": 42.3,
      "score_breakdown": {
        "trend_strength": 80.8,
        "trend_cleanliness": 100.0,
        "rs": 60.9,
        "base_setup": 14.6,
        "volume_profile": 47.3,
        "raw_setup_score": 60.4,
        "penalty_multiplier": 0.7,
        "penalty_triggered": [
          "reversal_mild",
          "52w_low_mild"
        ],
        "composite_score": 42.3
      },
      "indicators": {
        "ema_21": 29.6426,
        "ema_50": 27.0353,
        "ema_150": 24.1763,
        "ema_200": 23.4796,
        "ema_aligned": true,
        "ema_200_slope_pct": 0.205795,
        "rsi_14": 69.71,
        "macd": 1.9128,
        "macd_signal": 1.6442,
        "macd_hist": 0.2686,
        "macd_crossover_bullish": false,
        "adx_14": 39.97,
        "adx_trending": true,
        "obv_trend": "rising",
        "cmf_20": 0.2923,
        "rs_3m_percentile": 76.2,
        "rs_6m_percentile": 41.7,
        "ibd_rs_percentile": 60.1,
        "volume_ratio": 0.9,
        "vcp_detected": false,
        "vcp_score": 36.6,
        "vcp_contractions": 7,
        "vcp_tightness": 0.968,
        "squeeze_on": false,
        "squeeze_fired": false,
        "squeeze_bars": 0,
        "squeeze_score": 0.0,
        "extension_ema21_pct": 11.66,
        "extension_ema50_pct": 22.43,
        "atr_pct": 3.85,
        "extension_atr_multiple": 2.71,
        "max_gap_pct": 5.08,
        "is_extended": false,
        "sr_nearest_support": 24.47,
        "sr_support_touches": 3,
        "sr_support_dist_pct": 26.07,
        "sr_near_support": false
      },
      "stage2": false,
      "vcp": false,
      "squeeze": false,
      "chart_url": "https://raw.githubusercontent.com/ilyamiller14/stock-screener/main/results/charts/HPE_2026-05-15.png"
    },
    {
      "rank": 9,
      "ticker": "GLNG",
      "company_name": "Golar LNG Limited",
      "sector": "Energy",
      "industry": "Oil & Gas Midstream",
      "close": 57.04,
      "change_pct": -0.33,
      "volume": 1390729,
      "avg_volume_20d": 1349011,
      "high_52w": 57.79,
      "low_52w": 34.834,
      "dist_from_52w_high_pct": 1.3,
      "composite_score": 42.1,
      "score_breakdown": {
        "trend_strength": 76.3,
        "trend_cleanliness": 81.8,
        "rs": 37.2,
        "base_setup": 6.0,
        "volume_profile": 50.8,
        "raw_setup_score": 49.5,
        "penalty_multiplier": 0.85,
        "penalty_triggered": [
          "52w_low_mild"
        ],
        "composite_score": 42.1
      },
      "indicators": {
        "ema_21": 55.2285,
        "ema_50": 52.4792,
        "ema_150": 46.4489,
        "ema_200": 44.8542,
        "ema_aligned": true,
        "ema_200_slope_pct": 0.199074,
        "rsi_14": 62.87,
        "macd": 1.3043,
        "macd_signal": 1.2164,
        "macd_hist": 0.0879,
        "macd_crossover_bullish": true,
        "adx_14": 20.49,
        "adx_trending": true,
        "obv_trend": "rising",
        "cmf_20": 0.4326,
        "rs_3m_percentile": 57.7,
        "rs_6m_percentile": 49.4,
        "ibd_rs_percentile": 30.4,
        "volume_ratio": 1.03,
        "vcp_detected": false,
        "vcp_score": 15.0,
        "vcp_contractions": 5,
        "vcp_tightness": 1.289,
        "squeeze_on": false,
        "squeeze_fired": false,
        "squeeze_bars": 0,
        "squeeze_score": 0.0,
        "extension_ema21_pct": 3.28,
        "extension_ema50_pct": 8.69,
        "atr_pct": 2.7,
        "extension_atr_multiple": 1.18,
        "max_gap_pct": 3.67,
        "is_extended": false,
        "sr_nearest_support": 38.7,
        "sr_support_touches": 3,
        "sr_support_dist_pct": 32.16,
        "sr_near_support": false
      },
      "stage2": false,
      "vcp": false,
      "squeeze": false,
      "chart_url": "https://raw.githubusercontent.com/ilyamiller14/stock-screener/main/results/charts/GLNG_2026-05-15.png"
    },
    {
      "rank": 10,
      "ticker": "PBI",
      "company_name": "Pitney Bowes Inc.",
      "sector": "Industrials",
      "industry": "Integrated Freight & Logistics",
      "close": 15.75,
      "change_pct": -0.44,
      "volume": 1640822,
      "avg_volume_20d": 4340481,
      "high_52w": 16.52,
      "low_52w": 8.7964,
      "dist_from_52w_high_pct": 4.66,
      "composite_score": 41.5,
      "score_breakdown": {
        "trend_strength": 97.3,
        "trend_cleanliness": 76.7,
        "rs": 66.3,
        "base_setup": 0.0,
        "volume_profile": 45.8,
        "raw_setup_score": 59.3,
        "penalty_multiplier": 0.7,
        "penalty_triggered": [
          "climactic_mild",
          "exhaustion_gap_mild",
          "reversal_mild",
          "52w_low_mild"
        ],
        "composite_score": 41.5
      },
      "indicators": {
        "ema_21": 14.8837,
        "ema_50": 13.4049,
        "ema_150": 11.6691,
        "ema_200": 11.2492,
        "ema_aligned": true,
        "ema_200_slope_pct": 0.298586,
        "rsi_14": 67.44,
        "macd": 0.8492,
        "macd_signal": 0.979,
        "macd_hist": -0.1299,
        "macd_crossover_bullish": false,
        "adx_14": 39.43,
        "adx_trending": true,
        "obv_trend": "rising",
        "cmf_20": 0.2327,
        "rs_3m_percentile": 83.3,
        "rs_6m_percentile": 66.1,
        "ibd_rs_percentile": 63.1,
        "volume_ratio": 0.38,
        "vcp_detected": false,
        "vcp_score": 12.0,
        "vcp_contractions": 6,
        "vcp_tightness": 1.486,
        "squeeze_on": false,
        "squeeze_fired": false,
        "squeeze_bars": 0,
        "squeeze_score": 0.0,
        "extension_ema21_pct": 5.82,
        "extension_ema50_pct": 17.49,
        "atr_pct": 3.55,
        "extension_atr_multiple": 1.55,
        "max_gap_pct": 10.25,
        "is_extended": false,
        "sr_nearest_support": 10.67,
        "sr_support_touches": 4,
        "sr_support_dist_pct": 32.25,
        "sr_near_support": false
      },
      "stage2": false,
      "vcp": false,
      "squeeze": false,
      "chart_url": "https://raw.githubusercontent.com/ilyamiller14/stock-screener/main/results/charts/PBI_2026-05-15.png"
    },
    {
      "rank": 11,
      "ticker": "ENS",
      "company_name": "EnerSys",
      "sector": "Industrials",
      "industry": "Electrical Equipment & Parts",
      "close": 236.98,
      "change_pct": -1.11,
      "volume": 306850,
      "avg_volume_20d": 315107,
      "high_52w": 239.69,
      "low_52w": 75.9475,
      "dist_from_52w_high_pct": 1.13,
      "composite_score": 41.0,
      "score_breakdown": {
        "trend_strength": 98.5,
        "trend_cleanliness": 93.9,
        "rs": 76.4,
        "base_setup": 17.5,
        "volume_profile": 46.7,
        "raw_setup_score": 68.3,
        "penalty_multiplier": 0.6,
        "penalty_triggered": [
          "52w_low_heavy"
        ],
        "composite_score": 41.0
      },
      "indicators": {
        "ema_21": 218.2764,
        "ema_50": 200.0904,
        "ema_150": 168.4444,
        "ema_200": 158.3037,
        "ema_aligned": true,
        "ema_200_slope_pct": 0.281472,
        "rsi_14": 74.32,
        "macd": 12.747,
        "macd_signal": 11.5818,
        "macd_hist": 1.1651,
        "macd_crossover_bullish": false,
        "adx_14": 44.75,
        "adx_trending": true,
        "obv_trend": "rising",
        "cmf_20": 0.2669,
        "rs_3m_percentile": 59.5,
        "rs_6m_percentile": 69.0,
        "ibd_rs_percentile": 67.9,
        "volume_ratio": 0.97,
        "vcp_detected": false,
        "vcp_score": 43.8,
        "vcp_contractions": 4,
        "vcp_tightness": 0.925,
        "squeeze_on": false,
        "squeeze_fired": false,
        "squeeze_bars": 0,
        "squeeze_score": 0.0,
        "extension_ema21_pct": 8.57,
        "extension_ema50_pct": 18.44,
        "atr_pct": 2.97,
        "extension_atr_multiple": 2.66,
        "max_gap_pct": 4.91,
        "is_extended": false,
        "sr_nearest_support": 100.13,
        "sr_support_touches": 2,
        "sr_support_dist_pct": 57.75,
        "sr_near_support": false
      },
      "stage2": false,
      "vcp": false,
      "squeeze": false,
      "chart_url": "https://raw.githubusercontent.com/ilyamiller14/stock-screener/main/results/charts/ENS_2026-05-15.png"
    },
    {
      "rank": 12,
      "ticker": "TRGP",
      "company_name": "Targa Resources Corp.",
      "sector": "Energy",
      "industry": "Oil & Gas Midstream",
      "close": 271.99,
      "change_pct": 1.69,
      "volume": 1423208,
      "avg_volume_20d": 1212205,
      "high_52w": 273.0699,
      "low_52w": 141.7662,
      "dist_from_52w_high_pct": 0.4,
      "composite_score": 40.5,
      "score_breakdown": {
        "trend_strength": 76.7,
        "trend_cleanliness": 56.1,
        "rs": 38.1,
        "base_setup": 16.4,
        "volume_profile": 48.2,
        "raw_setup_score": 47.6,
        "penalty_multiplier": 0.85,
        "penalty_triggered": [
          "52w_low_mild"
        ],
        "composite_score": 40.5
      },
      "indicators": {
        "ema_21": 253.0828,
        "ema_50": 242.8806,
        "ema_150": 214.7675,
        "ema_200": 205.9626,
        "ema_aligned": true,
        "ema_200_slope_pct": 0.187482,
        "rsi_14": 69.69,
        "macd": 6.5214,
        "macd_signal": 4.7031,
        "macd_hist": 1.8183,
        "macd_crossover_bullish": false,
        "adx_14": 24.11,
        "adx_trending": true,
        "obv_trend": "rising",
        "cmf_20": 0.3289,
        "rs_3m_percentile": 40.5,
        "rs_6m_percentile": 57.7,
        "ibd_rs_percentile": 34.5,
        "volume_ratio": 1.17,
        "vcp_detected": false,
        "vcp_score": 24.7,
        "vcp_contractions": 7,
        "vcp_tightness": 1.267,
        "squeeze_on": false,
        "squeeze_fired": false,
        "squeeze_bars": 0,
        "squeeze_score": 0.0,
        "extension_ema21_pct": 7.47,
        "extension_ema50_pct": 11.99,
        "atr_pct": 2.69,
        "extension_atr_multiple": 2.59,
        "max_gap_pct": 3.15,
        "is_extended": false,
        "sr_nearest_support": 165.49,
        "sr_support_touches": 4,
        "sr_support_dist_pct": 39.15,
        "sr_near_support": false
      },
      "stage2": false,
      "vcp": false,
      "squeeze": false,
      "chart_url": "https://raw.githubusercontent.com/ilyamiller14/stock-screener/main/results/charts/TRGP_2026-05-15.png"
    },
    {
      "rank": 13,
      "ticker": "BTSG",
      "company_name": "BrightSpring Health Services, Inc.",
      "sector": "Healthcare",
      "industry": "Health Information Services",
      "close": 57.9,
      "change_pct": -0.86,
      "volume": 2833365,
      "avg_volume_20d": 3049388,
      "high_52w": 58.67,
      "low_52w": 19.01,
      "dist_from_52w_high_pct": 1.31,
      "composite_score": 40.4,
      "score_breakdown": {
        "trend_strength": 93.7,
        "trend_cleanliness": 92.8,
        "rs": 85.9,
        "base_setup": 6.0,
        "volume_profile": 48.9,
        "raw_setup_score": 67.4,
        "penalty_multiplier": 0.6,
        "penalty_triggered": [
          "52w_low_heavy"
        ],
        "composite_score": 40.4
      },
      "indicators": {
        "ema_21": 52.1271,
        "ema_50": 47.8557,
        "ema_150": 40.3646,
        "ema_200": 37.6727,
        "ema_aligned": true,
        "ema_200_slope_pct": 0.268938,
        "rsi_14": 75.68,
        "macd": 3.2176,
        "macd_signal": 2.6709,
        "macd_hist": 0.5467,
        "macd_crossover_bullish": false,
        "adx_14": 30.4,
        "adx_trending": true,
        "obv_trend": "rising",
        "cmf_20": 0.3553,
        "rs_3m_percentile": 78.6,
        "rs_6m_percentile": 70.2,
        "ibd_rs_percentile": 76.2,
        "volume_ratio": 0.93,
        "vcp_detected": false,
        "vcp_score": 15.0,
        "vcp_contractions": 7,
        "vcp_tightness": 2.853,
        "squeeze_on": false,
        "squeeze_fired": false,
        "squeeze_bars": 0,
        "squeeze_score": 0.0,
        "extension_ema21_pct": 11.07,
        "extension_ema50_pct": 20.99,
        "atr_pct": 3.46,
        "extension_atr_multiple": 2.88,
        "max_gap_pct": 4.11,
        "is_extended": false,
        "sr_nearest_support": 37.53,
        "sr_support_touches": 5,
        "sr_support_dist_pct": 35.18,
        "sr_near_support": false
      },
      "stage2": false,
      "vcp": false,
      "squeeze": false,
      "chart_url": "https://raw.githubusercontent.com/ilyamiller14/stock-screener/main/results/charts/BTSG_2026-05-15.png"
    },
    {
      "rank": 14,
      "ticker": "CPRX",
      "company_name": "Catalyst Pharmaceuticals, Inc.",
      "sector": "Healthcare",
      "industry": "Biotechnology",
      "close": 31.18,
      "change_pct": 0.06,
      "volume": 2264898,
      "avg_volume_20d": 3229639,
      "high_52w": 32.56,
      "low_52w": 19.05,
      "dist_from_52w_high_pct": 4.24,
      "composite_score": 40.4,
      "score_breakdown": {
        "trend_strength": 79.7,
        "trend_cleanliness": 78.5,
        "rs": 28.1,
        "base_setup": 16.0,
        "volume_profile": 37.0,
        "raw_setup_score": 47.5,
        "penalty_multiplier": 0.85,
        "penalty_triggered": [
          "52w_low_mild"
        ],
        "composite_score": 40.4
      },
      "indicators": {
        "ema_21": 29.3459,
        "ema_50": 27.2881,
        "ema_150": 24.7977,
        "ema_200": 24.1878,
        "ema_aligned": true,
        "ema_200_slope_pct": 0.1933,
        "rsi_14": 73.35,
        "macd": 1.5065,
        "macd_signal": 1.452,
        "macd_hist": 0.0545,
        "macd_crossover_bullish": false,
        "adx_14": 53.34,
        "adx_trending": true,
        "obv_trend": "rising",
        "cmf_20": -0.1218,
        "rs_3m_percentile": 53.0,
        "rs_6m_percentile": 33.3,
        "ibd_rs_percentile": 20.8,
        "volume_ratio": 0.7,
        "vcp_detected": false,
        "vcp_score": 40.0,
        "vcp_contractions": 7,
        "vcp_tightness": 0.284,
        "squeeze_on": false,
        "squeeze_fired": false,
        "squeeze_bars": 0,
        "squeeze_score": 0.0,
        "extension_ema21_pct": 6.25,
        "extension_ema50_pct": 14.26,
        "atr_pct": 2.41,
        "extension_atr_multiple": 2.44,
        "max_gap_pct": 2.04,
        "is_extended": false,
        "sr_nearest_support": 22.43,
        "sr_support_touches": 4,
        "sr_support_dist_pct": 28.06,
        "sr_near_support": false
      },
      "stage2": false,
      "vcp": false,
      "squeeze": false,
      "chart_url": "https://raw.githubusercontent.com/ilyamiller14/stock-screener/main/results/charts/CPRX_2026-05-15.png"
    },
    {
      "rank": 15,
      "ticker": "STT",
      "company_name": "State Street Corporation",
      "sector": "Financial Services",
      "industry": "Asset Management",
      "close": 152.85,
      "change_pct": -0.59,
      "volume": 1061358,
      "avg_volume_20d": 2053697,
      "high_52w": 156.18,
      "low_52w": 91.623,
      "dist_from_52w_high_pct": 2.13,
      "composite_score": 40.4,
      "score_breakdown": {
        "trend_strength": 73.7,
        "trend_cleanliness": 81.6,
        "rs": 30.0,
        "base_setup": 18.3,
        "volume_profile": 37.7,
        "raw_setup_score": 47.5,
        "penalty_multiplier": 0.85,
        "penalty_triggered": [
          "52w_low_mild"
        ],
        "composite_score": 40.4
      },
      "indicators": {
        "ema_21": 148.688,
        "ema_50": 141.5868,
        "ema_150": 129.1874,
        "ema_200": 124.7091,
        "ema_aligned": true,
        "ema_200_slope_pct": 0.189039,
        "rsi_14": 63.74,
        "macd": 3.6073,
        "macd_signal": 4.224,
        "macd_hist": -0.6167,
        "macd_crossover_bullish": false,
        "adx_14": 28.8,
        "adx_trending": true,
        "obv_trend": "rising",
        "cmf_20": 0.0276,
        "rs_3m_percentile": 36.9,
        "rs_6m_percentile": 25.0,
        "ibd_rs_percentile": 28.6,
        "volume_ratio": 0.52,
        "vcp_detected": false,
        "vcp_score": 10.1,
        "vcp_contractions": 7,
        "vcp_tightness": 2.105,
        "squeeze_on": false,
        "squeeze_fired": false,
        "squeeze_bars": 0,
        "squeeze_score": 0.0,
        "extension_ema21_pct": 2.8,
        "extension_ema50_pct": 7.95,
        "atr_pct": 2.13,
        "extension_atr_multiple": 1.28,
        "max_gap_pct": 2.45,
        "is_extended": false,
        "sr_nearest_support": 119.52,
        "sr_support_touches": 3,
        "sr_support_dist_pct": 21.8,
        "sr_near_support": false
      },
      "stage2": false,
      "vcp": false,
      "squeeze": false,
      "chart_url": "https://raw.githubusercontent.com/ilyamiller14/stock-screener/main/results/charts/STT_2026-05-15.png"
    },
    {
      "rank": 16,
      "ticker": "FCFS",
      "company_name": "FirstCash Holdings, Inc.",
      "sector": "Financial Services",
      "industry": "Credit Services",
      "close": 226.54,
      "change_pct": -0.44,
      "volume": 266491,
      "avg_volume_20d": 366029,
      "high_52w": 235.97,
      "low_52w": 118.264,
      "dist_from_52w_high_pct": 4.0,
      "composite_score": 40.2,
      "score_breakdown": {
        "trend_strength": 86.9,
        "trend_cleanliness": 92.7,
        "rs": 40.1,
        "base_setup": 29.9,
        "volume_profile": 38.6,
        "raw_setup_score": 57.4,
        "penalty_multiplier": 0.7,
        "penalty_triggered": [
          "reversal_mild",
          "52w_low_mild"
        ],
        "composite_score": 40.2
      },
      "indicators": {
        "ema_21": 219.7505,
        "ema_50": 207.6376,
        "ema_150": 183.2072,
        "ema_200": 175.0804,
        "ema_aligned": true,
        "ema_200_slope_pct": 0.22769,
        "rsi_14": 62.64,
        "macd": 7.1256,
        "macd_signal": 7.3815,
        "macd_hist": -0.256,
        "macd_crossover_bullish": false,
        "adx_14": 42.95,
        "adx_trending": true,
        "obv_trend": "rising",
        "cmf_20": 0.1063,
        "rs_3m_percentile": 48.2,
        "rs_6m_percentile": 39.3,
        "ibd_rs_percentile": 37.5,
        "volume_ratio": 0.73,
        "vcp_detected": false,
        "vcp_score": 12.0,
        "vcp_contractions": 6,
        "vcp_tightness": 1.536,
        "squeeze_on": false,
        "squeeze_fired": false,
        "squeeze_bars": 0,
        "squeeze_score": 0.0,
        "extension_ema21_pct": 3.09,
        "extension_ema50_pct": 9.1,
        "atr_pct": 2.97,
        "extension_atr_multiple": 1.01,
        "max_gap_pct": 4.93,
        "is_extended": false,
        "sr_nearest_support": 148.34,
        "sr_support_touches": 5,
        "sr_support_dist_pct": 34.52,
        "sr_near_support": false
      },
      "stage2": false,
      "vcp": false,
      "squeeze": false,
      "chart_url": "https://raw.githubusercontent.com/ilyamiller14/stock-screener/main/results/charts/FCFS_2026-05-15.png"
    },
    {
      "rank": 17,
      "ticker": "KGS",
      "company_name": "Kodiak Gas Services, Inc.",
      "sector": "Energy",
      "industry": "Oil & Gas Equipment & Services",
      "close": 73.49,
      "change_pct": -1.0,
      "volume": 5229289,
      "avg_volume_20d": 1932339,
      "high_52w": 76.68,
      "low_52w": 29.3723,
      "dist_from_52w_high_pct": 4.16,
      "composite_score": 39.8,
      "score_breakdown": {
        "trend_strength": 98.3,
        "trend_cleanliness": 90.0,
        "rs": 72.8,
        "base_setup": 14.3,
        "volume_profile": 48.5,
        "raw_setup_score": 66.4,
        "penalty_multiplier": 0.6,
        "penalty_triggered": [
          "climactic_mild",
          "reversal_mild",
          "52w_low_heavy"
        ],
        "composite_score": 39.8
      },
      "indicators": {
        "ema_21": 69.3623,
        "ema_50": 63.2954,
        "ema_150": 51.2823,
        "ema_200": 48.025,
        "ema_aligned": true,
        "ema_200_slope_pct": 0.323609,
        "rsi_14": 69.57,
        "macd": 3.6424,
        "macd_signal": 3.3887,
        "macd_hist": 0.2537,
        "macd_crossover_bullish": false,
        "adx_14": 64.49,
        "adx_trending": true,
        "obv_trend": "rising",
        "cmf_20": 0.3393,
        "rs_3m_percentile": 75.0,
        "rs_6m_percentile": 88.7,
        "ibd_rs_percentile": 70.8,
        "volume_ratio": 2.71,
        "vcp_detected": false,
        "vcp_score": 35.7,
        "vcp_contractions": 5,
        "vcp_tightness": 0.737,
        "squeeze_on": false,
        "squeeze_fired": false,
        "squeeze_bars": 0,
        "squeeze_score": 0.0,
        "extension_ema21_pct": 5.95,
        "extension_ema50_pct": 16.11,
        "atr_pct": 3.45,
        "extension_atr_multiple": 1.63,
        "max_gap_pct": 5.71,
        "is_extended": false,
        "sr_nearest_support": 32.63,
        "sr_support_touches": 3,
        "sr_support_dist_pct": 55.6,
        "sr_near_support": false
      },
      "stage2": false,
      "vcp": false,
      "squeeze": false,
      "chart_url": "https://raw.githubusercontent.com/ilyamiller14/stock-screener/main/results/charts/KGS_2026-05-15.png"
    },
    {
      "rank": 18,
      "ticker": "NUE",
      "company_name": "Nucor Corporation",
      "sector": "Basic Materials",
      "industry": "Steel",
      "close": 227.02,
      "change_pct": -2.5,
      "volume": 1336804,
      "avg_volume_20d": 1616290,
      "high_52w": 235.45,
      "low_52w": 104.6233,
      "dist_from_52w_high_pct": 3.58,
      "composite_score": 38.5,
      "score_breakdown": {
        "trend_strength": 94.9,
        "trend_cleanliness": 75.2,
        "rs": 46.3,
        "base_setup": 8.5,
        "volume_profile": 44.9,
        "raw_setup_score": 55.0,
        "penalty_multiplier": 0.7,
        "penalty_triggered": [
          "reversal_mild",
          "52w_low_mild"
        ],
        "composite_score": 38.5
      },
      "indicators": {
        "ema_21": 219.8526,
        "ema_50": 202.4953,
        "ema_150": 177.6126,
        "ema_200": 170.9771,
        "ema_aligned": true,
        "ema_200_slope_pct": 0.265999,
        "rsi_14": 64.18,
        "macd": 10.9305,
        "macd_signal": 12.1479,
        "macd_hist": -1.2175,
        "macd_crossover_bullish": false,
        "adx_14": 54.05,
        "adx_trending": true,
        "obv_trend": "rising",
        "cmf_20": 0.1957,
        "rs_3m_percentile": 46.4,
        "rs_6m_percentile": 51.2,
        "ibd_rs_percentile": 45.2,
        "volume_ratio": 0.83,
        "vcp_detected": false,
        "vcp_score": 7.5,
        "vcp_contractions": 5,
        "vcp_tightness": 3.897,
        "squeeze_on": false,
        "squeeze_fired": false,
        "squeeze_bars": 0,
        "squeeze_score": 0.0,
        "extension_ema21_pct": 3.26,
        "extension_ema50_pct": 12.11,
        "atr_pct": 2.46,
        "extension_atr_multiple": 1.29,
        "max_gap_pct": 3.04,
        "is_extended": false,
        "sr_nearest_support": 163.4,
        "sr_support_touches": 4,
        "sr_support_dist_pct": 28.02,
        "sr_near_support": false
      },
      "stage2": false,
      "vcp": false,
      "squeeze": false,
      "chart_url": "https://raw.githubusercontent.com/ilyamiller14/stock-screener/main/results/charts/NUE_2026-05-15.png"
    },
    {
      "rank": 19,
      "ticker": "MPC",
      "company_name": "Marathon Petroleum Corporation",
      "sector": "Energy",
      "industry": "Oil & Gas Refining & Marketing",
      "close": 255.03,
      "change_pct": 2.5,
      "volume": 1520134,
      "avg_volume_20d": 2244506,
      "high_52w": 261.61,
      "low_52w": 152.2603,
      "dist_from_52w_high_pct": 2.52,
      "composite_score": 38.3,
      "score_breakdown": {
        "trend_strength": 72.9,
        "trend_cleanliness": 51.9,
        "rs": 36.4,
        "base_setup": 15.7,
        "volume_profile": 45.7,
        "raw_setup_score": 45.1,
        "penalty_multiplier": 0.85,
        "penalty_triggered": [
          "52w_low_mild"
        ],
        "composite_score": 38.3
      },
      "indicators": {
        "ema_21": 242.9691,
        "ema_50": 232.362,
        "ema_150": 208.4663,
        "ema_200": 201.2882,
        "ema_aligned": true,
        "ema_200_slope_pct": 0.182854,
        "rsi_14": 62.08,
        "macd": 6.3445,
        "macd_signal": 5.5817,
        "macd_hist": 0.7629,
        "macd_crossover_bullish": false,
        "adx_14": 23.24,
        "adx_trending": true,
        "obv_trend": "rising",
        "cmf_20": 0.2267,
        "rs_3m_percentile": 50.6,
        "rs_6m_percentile": 28.0,
        "ibd_rs_percentile": 33.9,
        "volume_ratio": 0.68,
        "vcp_detected": false,
        "vcp_score": 39.2,
        "vcp_contractions": 5,
        "vcp_tightness": 0.574,
        "squeeze_on": false,
        "squeeze_fired": false,
        "squeeze_bars": 0,
        "squeeze_score": 0.0,
        "extension_ema21_pct": 4.96,
        "extension_ema50_pct": 9.76,
        "atr_pct": 3.29,
        "extension_atr_multiple": 1.44,
        "max_gap_pct": 4.85,
        "is_extended": false,
        "sr_nearest_support": 180.19,
        "sr_support_touches": 5,
        "sr_support_dist_pct": 29.35,
        "sr_near_support": false
      },
      "stage2": false,
      "vcp": false,
      "squeeze": false,
      "chart_url": "https://raw.githubusercontent.com/ilyamiller14/stock-screener/main/results/charts/MPC_2026-05-15.png"
    },
    {
      "rank": 20,
      "ticker": "ADI",
      "company_name": "ADI",
      "sector": "Unknown",
      "industry": "Unknown",
      "close": 417.49,
      "change_pct": -2.18,
      "volume": 3633700,
      "avg_volume_20d": 3482075,
      "high_52w": 435.72,
      "low_52w": 202.9043,
      "dist_from_52w_high_pct": 4.18,
      "composite_score": 36.1,
      "score_breakdown": {
        "trend_strength": 92.5,
        "trend_cleanliness": 56.4,
        "rs": 46.6,
        "base_setup": 11.3,
        "volume_profile": 41.0,
        "raw_setup_score": 51.6,
        "penalty_multiplier": 0.7,
        "penalty_triggered": [
          "reversal_mild",
          "52w_low_mild"
        ],
        "composite_score": 36.1
      },
      "indicators": {
        "ema_21": 400.0143,
        "ema_50": 370.552,
        "ema_150": 319.7405,
        "ema_200": 304.7568,
        "ema_aligned": true,
        "ema_200_slope_pct": 0.26505,
        "rsi_14": 63.25,
        "macd": 19.1696,
        "macd_signal": 19.1947,
        "macd_hist": -0.0251,
        "macd_crossover_bullish": false,
        "adx_14": 40.73,
        "adx_trending": true,
        "obv_trend": "rising",
        "cmf_20": 0.1538,
        "rs_3m_percentile": 45.8,
        "rs_6m_percentile": 72.0,
        "ibd_rs_percentile": 42.9,
        "volume_ratio": 1.04,
        "vcp_detected": false,
        "vcp_score": 28.2,
        "vcp_contractions": 3,
        "vcp_tightness": 1.698,
        "squeeze_on": false,
        "squeeze_fired": false,
        "squeeze_bars": 0,
        "squeeze_score": 0.0,
        "extension_ema21_pct": 4.37,
        "extension_ema50_pct": 12.67,
        "atr_pct": 2.81,
        "extension_atr_multiple": 1.49,
        "max_gap_pct": 5.62,
        "is_extended": false,
        "sr_nearest_support": 225.4,
        "sr_support_touches": 4,
        "sr_support_dist_pct": 46.01,
        "sr_near_support": false
      },
      "stage2": false,
      "vcp": false,
      "squeeze": false,
      "chart_url": "https://raw.githubusercontent.com/ilyamiller14/stock-screener/main/results/charts/ADI_2026-05-15.png"
    },
    {
      "rank": 21,
      "ticker": "BGC",
      "company_name": "BGC",
      "sector": "Unknown",
      "industry": "Unknown",
      "close": 11.19,
      "change_pct": -2.01,
      "volume": 3004423,
      "avg_volume_20d": 3082811,
      "high_52w": 11.91,
      "low_52w": 8.2334,
      "dist_from_52w_high_pct": 6.05,
      "composite_score": 35.9,
      "score_breakdown": {
        "trend_strength": 61.9,
        "trend_cleanliness": 80.3,
        "rs": 15.7,
        "base_setup": 4.9,
        "volume_profile": 22.8,
        "raw_setup_score": 35.9,
        "penalty_multiplier": 1.0,
        "penalty_triggered": [],
        "composite_score": 35.9
      },
      "indicators": {
        "ema_21": 11.1457,
        "ema_50": 10.6943,
        "ema_150": 9.9354,
        "ema_200": 9.7953,
        "ema_aligned": true,
        "ema_200_slope_pct": 0.140653,
        "rsi_14": 53.07,
        "macd": 0.1435,
        "macd_signal": 0.2012,
        "macd_hist": -0.0577,
        "macd_crossover_bullish": false,
        "adx_14": 24.05,
        "adx_trending": true,
        "obv_trend": "falling",
        "cmf_20": -0.0064,
        "rs_3m_percentile": 39.9,
        "rs_6m_percentile": 16.7,
        "ibd_rs_percentile": 8.9,
        "volume_ratio": 0.97,
        "vcp_detected": false,
        "vcp_score": 10.3,
        "vcp_contractions": 7,
        "vcp_tightness": 2.052,
        "squeeze_on": true,
        "squeeze_fired": false,
        "squeeze_bars": 1,
        "squeeze_score": 2.5,
        "extension_ema21_pct": 0.4,
        "extension_ema50_pct": 4.64,
        "atr_pct": 3.01,
        "extension_atr_multiple": 0.13,
        "max_gap_pct": 5.74,
        "is_extended": false,
        "sr_nearest_support": 9.72,
        "sr_support_touches": 5,
        "sr_support_dist_pct": 13.17,
        "sr_near_support": false
      },
      "stage2": false,
      "vcp": false,
      "squeeze": true,
      "chart_url": "https://raw.githubusercontent.com/ilyamiller14/stock-screener/main/results/charts/BGC_2026-05-15.png"
    },
    {
      "rank": 22,
      "ticker": "IBKR",
      "company_name": "IBKR",
      "sector": "Unknown",
      "industry": "Unknown",
      "close": 87.0,
      "change_pct": -1.45,
      "volume": 3772781,
      "avg_volume_20d": 4356659,
      "high_52w": 88.44,
      "low_52w": 48.9744,
      "dist_from_52w_high_pct": 1.63,
      "composite_score": 35.4,
      "score_breakdown": {
        "trend_strength": 70.6,
        "trend_cleanliness": 59.4,
        "rs": 28.5,
        "base_setup": 6.0,
        "volume_profile": 45.4,
        "raw_setup_score": 41.7,
        "penalty_multiplier": 0.85,
        "penalty_triggered": [
          "52w_low_mild"
        ],
        "composite_score": 35.4
      },
      "indicators": {
        "ema_21": 81.8364,
        "ema_50": 77.3188,
        "ema_150": 71.1205,
        "ema_200": 68.5188,
        "ema_aligned": true,
        "ema_200_slope_pct": 0.168594,
        "rsi_14": 66.65,
        "macd": 3.4155,
        "macd_signal": 3.1445,
        "macd_hist": 0.271,
        "macd_crossover_bullish": true,
        "adx_14": 26.61,
        "adx_trending": true,
        "obv_trend": "rising",
        "cmf_20": 0.2153,
        "rs_3m_percentile": 26.8,
        "rs_6m_percentile": 10.7,
        "ibd_rs_percentile": 31.0,
        "volume_ratio": 0.87,
        "vcp_detected": false,
        "vcp_score": 15.0,
        "vcp_contractions": 5,
        "vcp_tightness": 1.33,
        "squeeze_on": false,
        "squeeze_fired": false,
        "squeeze_bars": 0,
        "squeeze_score": 0.0,
        "extension_ema21_pct": 6.31,
        "extension_ema50_pct": 12.52,
        "atr_pct": 3.04,
        "extension_atr_multiple": 1.96,
        "max_gap_pct": 6.65,
        "is_extended": false,
        "sr_nearest_support": 64.19,
        "sr_support_touches": 4,
        "sr_support_dist_pct": 26.22,
        "sr_near_support": false
      },
      "stage2": false,
      "vcp": false,
      "squeeze": false,
      "chart_url": "https://raw.githubusercontent.com/ilyamiller14/stock-screener/main/results/charts/IBKR_2026-05-15.png"
    },
    {
      "rank": 23,
      "ticker": "POWI",
      "company_name": "POWI",
      "sector": "Unknown",
      "industry": "Unknown",
      "close": 73.24,
      "change_pct": 2.19,
      "volume": 1373092,
      "avg_volume_20d": 1401394,
      "high_52w": 81.59,
      "low_52w": 30.5318,
      "dist_from_52w_high_pct": 10.23,
      "composite_score": 35.3,
      "score_breakdown": {
        "trend_strength": 89.0,
        "trend_cleanliness": 93.0,
        "rs": 59.6,
        "base_setup": 7.2,
        "volume_profile": 42.4,
        "raw_setup_score": 58.9,
        "penalty_multiplier": 0.6,
        "penalty_triggered": [
          "52w_low_heavy"
        ],
        "composite_score": 35.3
      },
      "indicators": {
        "ema_21": 69.4261,
        "ema_50": 61.8443,
        "ema_150": 52.1262,
        "ema_200": 51.1365,
        "ema_aligned": true,
        "ema_200_slope_pct": 0.322633,
        "rsi_14": 60.89,
        "macd": 4.0192,
        "macd_signal": 4.8604,
        "macd_hist": -0.8412,
        "macd_crossover_bullish": false,
        "adx_14": 36.75,
        "adx_trending": true,
        "obv_trend": "rising",
        "cmf_20": 0.0953,
        "rs_3m_percentile": 83.9,
        "rs_6m_percentile": 87.5,
        "ibd_rs_percentile": 51.2,
        "volume_ratio": 0.98,
        "vcp_detected": false,
        "vcp_score": 18.0,
        "vcp_contractions": 6,
        "vcp_tightness": 1.211,
        "squeeze_on": false,
        "squeeze_fired": false,
        "squeeze_bars": 0,
        "squeeze_score": 0.0,
        "extension_ema21_pct": 5.49,
        "extension_ema50_pct": 18.43,
        "atr_pct": 5.82,
        "extension_atr_multiple": 0.89,
        "max_gap_pct": 7.5,
        "is_extended": false,
        "sr_nearest_support": 45.1,
        "sr_support_touches": 4,
        "sr_support_dist_pct": 38.42,
        "sr_near_support": false
      },
      "stage2": false,
      "vcp": false,
      "squeeze": false,
      "chart_url": "https://raw.githubusercontent.com/ilyamiller14/stock-screener/main/results/charts/POWI_2026-05-15.png"
    },
    {
      "rank": 24,
      "ticker": "LION",
      "company_name": "LION",
      "sector": "Unknown",
      "industry": "Unknown",
      "close": 12.64,
      "change_pct": -0.16,
      "volume": 2609703,
      "avg_volume_20d": 4206195,
      "high_52w": 13.01,
      "low_52w": 5.545,
      "dist_from_52w_high_pct": 2.84,
      "composite_score": 34.6,
      "score_breakdown": {
        "trend_strength": 90.1,
        "trend_cleanliness": 91.2,
        "rs": 70.3,
        "base_setup": 0.0,
        "volume_profile": 26.1,
        "raw_setup_score": 57.7,
        "penalty_multiplier": 0.6,
        "penalty_triggered": [
          "climactic_mild",
          "52w_low_heavy"
        ],
        "composite_score": 34.6
      },
      "indicators": {
        "ema_21": 12.0644,
        "ema_50": 11.1557,
        "ema_150": 9.4857,
        "ema_200": 9.0476,
        "ema_aligned": true,
        "ema_200_slope_pct": 0.283688,
        "rsi_14": 64.08,
        "macd": 0.4775,
        "macd_signal": 0.5388,
        "macd_hist": -0.0613,
        "macd_crossover_bullish": false,
        "adx_14": 29.57,
        "adx_trending": true,
        "obv_trend": "falling",
        "cmf_20": -0.0349,
        "rs_3m_percentile": 84.5,
        "rs_6m_percentile": 81.5,
        "ibd_rs_percentile": 66.1,
        "volume_ratio": 0.62,
        "vcp_detected": false,
        "vcp_score": 18.0,
        "vcp_contractions": 6,
        "vcp_tightness": 1.117,
        "squeeze_on": false,
        "squeeze_fired": false,
        "squeeze_bars": 0,
        "squeeze_score": 0.0,
        "extension_ema21_pct": 4.77,
        "extension_ema50_pct": 13.31,
        "atr_pct": 4.0,
        "extension_atr_multiple": 1.14,
        "max_gap_pct": 9.36,
        "is_extended": false,
        "sr_nearest_support": 6.5,
        "sr_support_touches": 3,
        "sr_support_dist_pct": 48.58,
        "sr_near_support": false
      },
      "stage2": false,
      "vcp": false,
      "squeeze": false,
      "chart_url": "https://raw.githubusercontent.com/ilyamiller14/stock-screener/main/results/charts/LION_2026-05-15.png"
    },
    {
      "rank": 25,
      "ticker": "AESI",
      "company_name": "AESI",
      "sector": "Unknown",
      "industry": "Unknown",
      "close": 18.87,
      "change_pct": -0.58,
      "volume": 2904189,
      "avg_volume_20d": 5231759,
      "high_52w": 19.61,
      "low_52w": 7.642,
      "dist_from_52w_high_pct": 3.77,
      "composite_score": 34.6,
      "score_breakdown": {
        "trend_strength": 86.1,
        "trend_cleanliness": 78.5,
        "rs": 68.2,
        "base_setup": 0.0,
        "volume_profile": 49.1,
        "raw_setup_score": 57.7,
        "penalty_multiplier": 0.6,
        "penalty_triggered": [
          "climactic_mild",
          "52w_low_heavy"
        ],
        "composite_score": 34.6
      },
      "indicators": {
        "ema_21": 17.2234,
        "ema_50": 15.1801,
        "ema_150": 13.1189,
        "ema_200": 13.0778,
        "ema_aligned": true,
        "ema_200_slope_pct": 0.275182,
        "rsi_14": 70.24,
        "macd": 1.4191,
        "macd_signal": 1.4242,
        "macd_hist": -0.0051,
        "macd_crossover_bullish": false,
        "adx_14": 38.11,
        "adx_trending": true,
        "obv_trend": "rising",
        "cmf_20": 0.3649,
        "rs_3m_percentile": 86.9,
        "rs_6m_percentile": 90.5,
        "ibd_rs_percentile": 62.5,
        "volume_ratio": 0.56,
        "vcp_detected": false,
        "vcp_score": 15.0,
        "vcp_contractions": 5,
        "vcp_tightness": 1.833,
        "squeeze_on": false,
        "squeeze_fired": false,
        "squeeze_bars": 0,
        "squeeze_score": 0.0,
        "extension_ema21_pct": 9.56,
        "extension_ema50_pct": 24.31,
        "atr_pct": 5.0,
        "extension_atr_multiple": 1.75,
        "max_gap_pct": 5.16,
        "is_extended": false,
        "sr_nearest_support": 11.91,
        "sr_support_touches": 6,
        "sr_support_dist_pct": 36.88,
        "sr_near_support": false
      },
      "stage2": false,
      "vcp": false,
      "squeeze": false,
      "chart_url": "https://raw.githubusercontent.com/ilyamiller14/stock-screener/main/results/charts/AESI_2026-05-15.png"
    }
  ],
  "macro": {
    "etfs": [
      {
        "ticker": "HYG",
        "interest_score": 80,
        "narrative": "Breaking below support at 79.58 (11 touches)",
        "sr_levels": [
          {
            "price": 77.8211,
            "touches": 17,
            "type": "support"
          },
          {
            "price": 79.5814,
            "touches": 11,
            "type": "resistance"
          }
        ],
        "rsi": 43.5,
        "chart_url": "https://raw.githubusercontent.com/ilyamiller14/stock-screener/main/results/charts/macro_HYG_2026-05-15.png",
        "chart_generated": true
      },
      {
        "ticker": "XLY",
        "interest_score": 65,
        "narrative": "Breaking below support at 117.51 (7 touches)",
        "sr_levels": [
          {
            "price": 117.5106,
            "touches": 7,
            "type": "resistance"
          },
          {
            "price": 114.0253,
            "touches": 6,
            "type": "support"
          },
          {
            "price": 120.3959,
            "touches": 5,
            "type": "resistance"
          },
          {
            "price": 104.4197,
            "touches": 4,
            "type": "support"
          },
          {
            "price": 122.8831,
            "touches": 3,
            "type": "resistance"
          }
        ],
        "rsi": 46.9,
        "chart_url": "https://raw.githubusercontent.com/ilyamiller14/stock-screener/main/results/charts/macro_XLY_2026-05-15.png",
        "chart_generated": true
      },
      {
        "ticker": "TLT",
        "interest_score": 65,
        "narrative": "Breaking above resistance at 82.95 (6 touches)",
        "sr_levels": [
          {
            "price": 86.08,
            "touches": 21,
            "type": "resistance"
          },
          {
            "price": 82.9545,
            "touches": 6,
            "type": "support"
          },
          {
            "price": 88.1361,
            "touches": 3,
            "type": "resistance"
          },
          {
            "price": 89.7682,
            "touches": 2,
            "type": "resistance"
          }
        ],
        "rsi": 33.1,
        "chart_url": "https://raw.githubusercontent.com/ilyamiller14/stock-screener/main/results/charts/macro_TLT_2026-05-15.png",
        "chart_generated": true
      },
      {
        "ticker": "SPLV",
        "interest_score": 60,
        "narrative": "Testing support at 72.33 (14 touches)",
        "sr_levels": [
          {
            "price": 70.8979,
            "touches": 14,
            "type": "support"
          },
          {
            "price": 72.3332,
            "touches": 14,
            "type": "support"
          },
          {
            "price": 74.543,
            "touches": 3,
            "type": "resistance"
          }
        ],
        "rsi": 38.7,
        "chart_url": "https://raw.githubusercontent.com/ilyamiller14/stock-screener/main/results/charts/macro_SPLV_2026-05-15.png",
        "chart_generated": true
      },
      {
        "ticker": "KRE",
        "interest_score": 44,
        "narrative": "Testing support at 66.31 (2 touches)",
        "sr_levels": [
          {
            "price": 70.0709,
            "touches": 8,
            "type": "resistance"
          },
          {
            "price": 62.2193,
            "touches": 7,
            "type": "support"
          },
          {
            "price": 57.6164,
            "touches": 4,
            "type": "support"
          },
          {
            "price": 60.4881,
            "touches": 3,
            "type": "support"
          },
          {
            "price": 64.9394,
            "touches": 3,
            "type": "support"
          }
        ],
        "rsi": 41.6,
        "chart_url": "https://raw.githubusercontent.com/ilyamiller14/stock-screener/main/results/charts/macro_KRE_2026-05-15.png",
        "chart_generated": true
      }
    ],
    "ratios": [
      {
        "pair": "XLY/XLP",
        "name": "Discretionary / Staples",
        "rising": "Risk appetite",
        "falling": "Defensive rotation",
        "interest_score": 70,
        "narrative": "Breaking below support at 1.38 (5 touches)",
        "sr_levels": [
          {
            "price": 1.3495,
            "touches": 5,
            "type": "support"
          },
          {
            "price": 1.3769,
            "touches": 5,
            "type": "resistance"
          },
          {
            "price": 1.3042,
            "touches": 4,
            "type": "support"
          },
          {
            "price": 1.4502,
            "touches": 4,
            "type": "resistance"
          },
          {
            "price": 1.4803,
            "touches": 3,
            "type": "resistance"
          }
        ],
        "rsi": 41.2,
        "chart_url": "https://raw.githubusercontent.com/ilyamiller14/stock-screener/main/results/charts/ratio_XLY_XLP_2026-05-15.png",
        "chart_generated": true
      },
      {
        "pair": "IWM/SPY",
        "name": "Small Cap / Large Cap",
        "rising": "Small-cap leadership",
        "falling": "Large-cap dominance",
        "interest_score": 65,
        "narrative": "Breaking above resistance at 0.37 (7 touches)",
        "sr_levels": [
          {
            "price": 0.3603,
            "touches": 10,
            "type": "support"
          },
          {
            "price": 0.3499,
            "touches": 7,
            "type": "support"
          },
          {
            "price": 0.3718,
            "touches": 7,
            "type": "support"
          },
          {
            "price": 0.3836,
            "touches": 3,
            "type": "resistance"
          },
          {
            "price": 0.3913,
            "touches": 3,
            "type": "resistance"
          }
        ],
        "rsi": 33.0,
        "chart_url": "https://raw.githubusercontent.com/ilyamiller14/stock-screener/main/results/charts/ratio_IWM_SPY_2026-05-15.png",
        "chart_generated": true
      },
      {
        "pair": "HYG/TLT",
        "name": "High Yield / Treasuries",
        "rising": "Credit confidence",
        "falling": "Flight to safety",
        "interest_score": 40,
        "narrative": "Testing support at 0.92 (16 touches) | Overbought",
        "sr_levels": [
          {
            "price": 0.9228,
            "touches": 16,
            "type": "support"
          },
          {
            "price": 0.8988,
            "touches": 15,
            "type": "support"
          }
        ],
        "rsi": 70.0,
        "chart_url": "https://raw.githubusercontent.com/ilyamiller14/stock-screener/main/results/charts/ratio_HYG_TLT_2026-05-15.png",
        "chart_generated": true
      }
    ]
  }
}